dr3/tp1/gowin/src/seven_segment_decoder.v
`timescale 1ns / 1ps

module seven_segment_decoder (
    input wire [3:0] value,
    input wire error,
    input wire success,
    output reg [6:0] seg
);

    /*
     * Common cathode display, active-high outputs.
     * Bit order: seg[0]=A, seg[1]=B, seg[2]=C, seg[3]=D,
     * seg[4]=E, seg[5]=F, seg[6]=G.
     */
    always @* begin
        if (error) begin
            seg = 7'b1111001;      // E
        end else if (success) begin
            seg = 7'b1101101;      // S
        end else begin
            case (value)
                4'd0: seg = 7'b0111111;
                4'd1: seg = 7'b0000110;
                4'd2: seg = 7'b1011011;
                4'd3: seg = 7'b1001111;
                4'd4: seg = 7'b1100110;
                default: seg = 7'b0000000;
            endcase
        end
    end

endmodule

dr3/tp1/gowin/src/sequence_fsm.v
`timescale 1ns / 1ps

module sequence_fsm #(
    parameter DISPLAY_TICKS = 27000000,
    parameter TICK_WIDTH = 25
) (
    input wire clk,
    input wire rst_n,
    input wire [3:0] button_pulse,
    output reg [3:0] led_n,
    output reg [3:0] display_value,
    output reg display_error,
    output reg display_success,
    output wire [2:0] state_debug,
    output wire [1:0] step_debug
);

    localparam STATE_IDLE       = 3'd0;
    localparam STATE_SHOW       = 3'd1;
    localparam STATE_WAIT_INPUT = 3'd2;
    localparam STATE_ERROR      = 3'd3;
    localparam STATE_SUCCESS    = 3'd4;

    reg [2:0] state;
    reg [2:0] next_state;
    reg [1:0] show_index;
    reg [1:0] next_show_index;
    reg [1:0] input_index;
    reg [1:0] next_input_index;
    reg [TICK_WIDTH-1:0] tick_count;
    reg [TICK_WIDTH-1:0] next_tick_count;

    assign state_debug = state;
    assign step_debug = (state == STATE_WAIT_INPUT) ? input_index : show_index;

    function [1:0] sequence_at;
        input [1:0] index;
        begin
            case (index)
                2'd0: sequence_at = 2'd0;
                2'd1: sequence_at = 2'd2;
                2'd2: sequence_at = 2'd1;
                default: sequence_at = 2'd3;
            endcase
        end
    endfunction

    function is_onehot;
        input [3:0] value;
        begin
            case (value)
                4'b0001,
                4'b0010,
                4'b0100,
                4'b1000: is_onehot = 1'b1;
                default: is_onehot = 1'b0;
            endcase
        end
    endfunction

    function [1:0] pulse_to_index;
        input [3:0] value;
        begin
            case (value)
                4'b0001: pulse_to_index = 2'd0;
                4'b0010: pulse_to_index = 2'd1;
                4'b0100: pulse_to_index = 2'd2;
                default: pulse_to_index = 2'd3;
            endcase
        end
    endfunction

    always @(posedge clk or negedge rst_n) begin
        if (!rst_n) begin
            state <= STATE_IDLE;
            show_index <= 2'd0;
            input_index <= 2'd0;
            tick_count <= {TICK_WIDTH{1'b0}};
        end else begin
            state <= next_state;
            show_index <= next_show_index;
            input_index <= next_input_index;
            tick_count <= next_tick_count;
        end
    end

    always @* begin
        next_state = state;
        next_show_index = show_index;
        next_input_index = input_index;
        next_tick_count = tick_count;

        case (state)
            STATE_IDLE: begin
                next_state = STATE_SHOW;
                next_show_index = 2'd0;
                next_input_index = 2'd0;
                next_tick_count = {TICK_WIDTH{1'b0}};
            end

            STATE_SHOW: begin
                if (tick_count == DISPLAY_TICKS - 1) begin
                    next_tick_count = {TICK_WIDTH{1'b0}};
                    if (show_index == 2'd3) begin
                        next_state = STATE_WAIT_INPUT;
                        next_show_index = 2'd0;
                        next_input_index = 2'd0;
                    end else begin
                        next_show_index = show_index + 1'b1;
                    end
                end else begin
                    next_tick_count = tick_count + 1'b1;
                end
            end

            STATE_WAIT_INPUT: begin
                if (button_pulse != 4'b0000) begin
                    if (!is_onehot(button_pulse)) begin
                        next_state = STATE_ERROR;
                    end else if (pulse_to_index(button_pulse) == sequence_at(input_index)) begin
                        if (input_index == 2'd3) begin
                            next_state = STATE_SUCCESS;
                        end else begin
                            next_input_index = input_index + 1'b1;
                        end
                    end else begin
                        next_state = STATE_ERROR;
                    end
                end
            end

            STATE_ERROR: begin
                next_state = STATE_ERROR;
            end

            STATE_SUCCESS: begin
                next_state = STATE_SUCCESS;
            end

            default: begin
                next_state = STATE_IDLE;
                next_show_index = 2'd0;
                next_input_index = 2'd0;
                next_tick_count = {TICK_WIDTH{1'b0}};
            end
        endcase
    end

    always @* begin
        led_n = 4'b1111;
        display_value = 4'd0;
        display_error = 1'b0;
        display_success = 1'b0;

        case (state)
            STATE_IDLE: begin
                display_value = 4'd0;
            end

            STATE_SHOW: begin
                led_n[sequence_at(show_index)] = 1'b0;
                display_value = {2'b00, show_index} + 4'd1;
            end

            STATE_WAIT_INPUT: begin
                display_value = {2'b00, input_index};
            end

            STATE_ERROR: begin
                display_error = 1'b1;
            end

            STATE_SUCCESS: begin
                display_success = 1'b1;
                display_value = 4'd4;
            end

            default: begin
                display_value = 4'd0;
            end
        endcase
    end

endmodule

dr3/tp1/gowin/src/button_conditioner.v
`timescale 1ns / 1ps

module button_conditioner #(
    parameter DEBOUNCE_TICKS = 270000,
    parameter COUNTER_WIDTH = 19
) (
    input wire clk,
    input wire rst_n,
    input wire raw_n,
    output reg pressed,
    output reg pressed_pulse
);

    reg sync_0;
    reg sync_1;
    reg [COUNTER_WIDTH-1:0] debounce_count;

    wire sampled_pressed;
    assign sampled_pressed = ~sync_1;

    always @(posedge clk or negedge rst_n) begin
        if (!rst_n) begin
            sync_0 <= 1'b1;
            sync_1 <= 1'b1;
        end else begin
            sync_0 <= raw_n;
            sync_1 <= sync_0;
        end
    end

    always @(posedge clk or negedge rst_n) begin
        if (!rst_n) begin
            pressed <= 1'b0;
            pressed_pulse <= 1'b0;
            debounce_count <= {COUNTER_WIDTH{1'b0}};
        end else begin
            pressed_pulse <= 1'b0;

            if (sampled_pressed == pressed) begin
                debounce_count <= {COUNTER_WIDTH{1'b0}};
            end else if (debounce_count == DEBOUNCE_TICKS - 1) begin
                pressed <= sampled_pressed;
                pressed_pulse <= sampled_pressed;
                debounce_count <= {COUNTER_WIDTH{1'b0}};
            end else begin
                debounce_count <= debounce_count + 1'b1;
            end
        end
    end

endmodule

dr3/tp1/gowin/src/sequence_validator_top.v
`timescale 1ns / 1ps

module sequence_validator_top #(
    parameter DISPLAY_TICKS = 27000000,
    parameter TICK_WIDTH = 25,
    parameter DEBOUNCE_TICKS = 270000,
    parameter DEBOUNCE_WIDTH = 19
) (
    input wire sys_clk,
    input wire sys_rst_n,
    input wire [3:0] btn_n,
    output wire [3:0] led_n,
    output wire seg_a,
    output wire seg_b,
    output wire seg_c,
    output wire seg_d,
    output wire seg_e,
    output wire seg_f,
    output wire seg_g
);

    wire [3:0] button_pressed;
    wire [3:0] button_pulse;
    wire [3:0] display_value;
    wire [6:0] seg_bus;
    wire display_error;
    wire display_success;
    wire [2:0] state_debug;
    wire [1:0] step_debug;

    genvar button_index;
    generate
        for (button_index = 0; button_index < 4; button_index = button_index + 1) begin : button_inputs
            button_conditioner #(
                .DEBOUNCE_TICKS(DEBOUNCE_TICKS),
                .COUNTER_WIDTH(DEBOUNCE_WIDTH)
            ) button_conditioner_inst (
                .clk(sys_clk),
                .rst_n(sys_rst_n),
                .raw_n(btn_n[button_index]),
                .pressed(button_pressed[button_index]),
                .pressed_pulse(button_pulse[button_index])
            );
        end
    endgenerate

    sequence_fsm #(
        .DISPLAY_TICKS(DISPLAY_TICKS),
        .TICK_WIDTH(TICK_WIDTH)
    ) sequence_fsm_inst (
        .clk(sys_clk),
        .rst_n(sys_rst_n),
        .button_pulse(button_pulse),
        .led_n(led_n),
        .display_value(display_value),
        .display_error(display_error),
        .display_success(display_success),
        .state_debug(state_debug),
        .step_debug(step_debug)
    );

    seven_segment_decoder seven_segment_decoder_inst (
        .value(display_value),
        .error(display_error),
        .success(display_success),
        .seg(seg_bus)
    );

    assign seg_a = seg_bus[0];
    assign seg_b = seg_bus[1];
    assign seg_c = seg_bus[2];
    assign seg_d = seg_bus[3];
    assign seg_e = seg_bus[4];
    assign seg_f = seg_bus[5];
    assign seg_g = seg_bus[6];

endmodule

dr3/tp1/sim/tb_sequence_validator.v
`timescale 1ns / 1ps

module tb_sequence_validator;

    localparam STATE_IDLE       = 3'd0;
    localparam STATE_SHOW       = 3'd1;
    localparam STATE_WAIT_INPUT = 3'd2;
    localparam STATE_ERROR      = 3'd3;
    localparam STATE_SUCCESS    = 3'd4;

    reg sys_clk;
    reg sys_rst_n;
    reg [3:0] btn_n;
    wire [3:0] led_n;
    wire seg_a;
    wire seg_b;
    wire seg_c;
    wire seg_d;
    wire seg_e;
    wire seg_f;
    wire seg_g;

    integer errors;

    sequence_validator_top #(
        .DISPLAY_TICKS(4),
        .TICK_WIDTH(4),
        .DEBOUNCE_TICKS(2),
        .DEBOUNCE_WIDTH(2)
    ) dut (
        .sys_clk(sys_clk),
        .sys_rst_n(sys_rst_n),
        .btn_n(btn_n),
        .led_n(led_n),
        .seg_a(seg_a),
        .seg_b(seg_b),
        .seg_c(seg_c),
        .seg_d(seg_d),
        .seg_e(seg_e),
        .seg_f(seg_f),
        .seg_g(seg_g)
    );

    initial begin
        sys_clk = 1'b0;
        forever #5 sys_clk = ~sys_clk;
    end

    initial begin
        $dumpfile("sim/build/tb_sequence_validator.vcd");
        $dumpvars(0, tb_sequence_validator);

        errors = 0;
        sys_rst_n = 1'b0;
        btn_n = 4'b1111;

        test_show_sequence;
        test_success_path;
        test_error_on_first_input;
        test_error_in_middle;
        test_simultaneous_buttons;
        test_reset_restarts_after_error;

        if (errors == 0) begin
            $display("ALL TESTS PASSED");
            $finish;
        end else begin
            $display("TESTS FAILED: %0d error(s)", errors);
            $fatal;
        end
    end

    task check;
        input condition;
        input [1023:0] message;
        begin
            if (!condition) begin
                $display("FAIL: %0s", message);
                errors = errors + 1;
            end else begin
                $display("PASS: %0s", message);
            end
        end
    endtask

    task do_reset;
        begin
            btn_n = 4'b1111;
            sys_rst_n = 1'b0;
            repeat (4) @(posedge sys_clk);
            sys_rst_n = 1'b1;
            repeat (2) @(posedge sys_clk);
        end
    endtask

    task wait_for_state;
        input [2:0] target_state;
        integer timeout;
        begin
            timeout = 0;
            while ((dut.state_debug !== target_state) && (timeout < 200)) begin
                @(posedge sys_clk);
                timeout = timeout + 1;
            end
            check(timeout < 200, "state reached before timeout");
        end
    endtask

    task wait_for_input_phase;
        begin
            wait_for_state(STATE_WAIT_INPUT);
            check(led_n == 4'b1111, "all leds off while waiting for input");
        end
    endtask

    task press_mask;
        input [3:0] mask;
        begin
            btn_n = ~mask;
            repeat (8) @(posedge sys_clk);
            btn_n = 4'b1111;
            repeat (8) @(posedge sys_clk);
        end
    endtask

    task press_button;
        input [1:0] index;
        begin
            case (index)
                2'd0: press_mask(4'b0001);
                2'd1: press_mask(4'b0010);
                2'd2: press_mask(4'b0100);
                default: press_mask(4'b1000);
            endcase
        end
    endtask

    task test_show_sequence;
        begin
            $display("TEST: show sequence LED0, LED2, LED1, LED3");
            do_reset;
            wait_for_state(STATE_SHOW);
            check(led_n == 4'b1110, "show step 1 lights LED0");
            repeat (4) @(posedge sys_clk);
            check(led_n == 4'b1011, "show step 2 lights LED2");
            repeat (4) @(posedge sys_clk);
            check(led_n == 4'b1101, "show step 3 lights LED1");
            repeat (4) @(posedge sys_clk);
            check(led_n == 4'b0111, "show step 4 lights LED3");
            wait_for_input_phase;
        end
    endtask

    task test_success_path;
        begin
            $display("TEST: success path 0,2,1,3");
            do_reset;
            wait_for_input_phase;
            press_button(2'd0);
            check(dut.step_debug == 2'd1, "first correct input advances progress");
            press_button(2'd2);
            check(dut.step_debug == 2'd2, "second correct input advances progress");
            press_button(2'd1);
            check(dut.step_debug == 2'd3, "third correct input advances progress");
            press_button(2'd3);
            wait_for_state(STATE_SUCCESS);
            check(dut.display_success == 1'b1, "success display flag is active");
            check({seg_g, seg_f, seg_e, seg_d, seg_c, seg_b, seg_a} == 7'b1101101,
                  "seven segment shows S on success");
            repeat (10) @(posedge sys_clk);
            check(dut.state_debug == STATE_SUCCESS, "success state is latched until reset");
        end
    endtask

    task test_error_on_first_input;
        begin
            $display("TEST: error on first input");
            do_reset;
            wait_for_input_phase;
            press_button(2'd1);
            wait_for_state(STATE_ERROR);
            check(dut.display_error == 1'b1, "error display flag is active");
            check({seg_g, seg_f, seg_e, seg_d, seg_c, seg_b, seg_a} == 7'b1111001,
                  "seven segment shows E on error");
            repeat (10) @(posedge sys_clk);
            check(dut.state_debug == STATE_ERROR, "error state is latched until reset");
        end
    endtask

    task test_error_in_middle;
        begin
            $display("TEST: error after partial correct sequence");
            do_reset;
            wait_for_input_phase;
            press_button(2'd0);
            check(dut.step_debug == 2'd1, "partial sequence accepted first input");
            press_button(2'd3);
            wait_for_state(STATE_ERROR);
            check(dut.display_error == 1'b1, "wrong middle input triggers error");
        end
    endtask

    task test_simultaneous_buttons;
        begin
            $display("TEST: simultaneous buttons trigger error");
            do_reset;
            wait_for_input_phase;
            press_mask(4'b0101);
            wait_for_state(STATE_ERROR);
            check(dut.display_error == 1'b1, "multiple simultaneous inputs trigger error");
        end
    endtask

    task test_reset_restarts_after_error;
        begin
            $display("TEST: reset restarts after error");
            do_reset;
            wait_for_input_phase;
            press_button(2'd1);
            wait_for_state(STATE_ERROR);
            do_reset;
            wait_for_input_phase;
            check(dut.state_debug == STATE_WAIT_INPUT, "reset restarts cycle after error");
            press_button(2'd0);
            press_button(2'd2);
            press_button(2'd1);
            press_button(2'd3);
            wait_for_state(STATE_SUCCESS);
            check(dut.display_success == 1'b1, "success works after reset");
        end
    endtask

endmodule

dr3/tp1/sim/build/tb_sequence_validator.vcd
$date
	Sun May  3 18:38:59 2026
$end
$version
	Icarus Verilog
$end
$timescale
	1ps
$end
$scope module tb_sequence_validator $end
$var wire 1 ! seg_g $end
$var wire 1 " seg_f $end
$var wire 1 # seg_e $end
$var wire 1 $ seg_d $end
$var wire 1 % seg_c $end
$var wire 1 & seg_b $end
$var wire 1 ' seg_a $end
$var wire 4 ( led_n [3:0] $end
$var reg 4 ) btn_n [3:0] $end
$var reg 1 * sys_clk $end
$var reg 1 + sys_rst_n $end
$var integer 32 , errors [31:0] $end
$scope module dut $end
$var wire 4 - btn_n [3:0] $end
$var wire 1 * sys_clk $end
$var wire 1 + sys_rst_n $end
$var wire 2 . step_debug [1:0] $end
$var wire 3 / state_debug [2:0] $end
$var wire 1 ! seg_g $end
$var wire 1 " seg_f $end
$var wire 1 # seg_e $end
$var wire 1 $ seg_d $end
$var wire 1 % seg_c $end
$var wire 7 0 seg_bus [6:0] $end
$var wire 1 & seg_b $end
$var wire 1 ' seg_a $end
$var wire 4 1 led_n [3:0] $end
$var wire 4 2 display_value [3:0] $end
$var wire 1 3 display_success $end
$var wire 1 4 display_error $end
$var wire 4 5 button_pulse [3:0] $end
$var wire 4 6 button_pressed [3:0] $end
$scope begin button_inputs[0] $end
$scope module button_conditioner_inst $end
$var wire 1 * clk $end
$var wire 1 7 raw_n $end
$var wire 1 + rst_n $end
$var wire 1 8 sampled_pressed $end
$var reg 2 9 debounce_count [1:0] $end
$var reg 1 : pressed $end
$var reg 1 ; pressed_pulse $end
$var reg 1 < sync_0 $end
$var reg 1 = sync_1 $end
$upscope $end
$upscope $end
$scope begin button_inputs[1] $end
$scope module button_conditioner_inst $end
$var wire 1 * clk $end
$var wire 1 > raw_n $end
$var wire 1 + rst_n $end
$var wire 1 ? sampled_pressed $end
$var reg 2 @ debounce_count [1:0] $end
$var reg 1 A pressed $end
$var reg 1 B pressed_pulse $end
$var reg 1 C sync_0 $end
$var reg 1 D sync_1 $end
$upscope $end
$upscope $end
$scope begin button_inputs[2] $end
$scope module button_conditioner_inst $end
$var wire 1 * clk $end
$var wire 1 E raw_n $end
$var wire 1 + rst_n $end
$var wire 1 F sampled_pressed $end
$var reg 2 G debounce_count [1:0] $end
$var reg 1 H pressed $end
$var reg 1 I pressed_pulse $end
$var reg 1 J sync_0 $end
$var reg 1 K sync_1 $end
$upscope $end
$upscope $end
$scope begin button_inputs[3] $end
$scope module button_conditioner_inst $end
$var wire 1 * clk $end
$var wire 1 L raw_n $end
$var wire 1 + rst_n $end
$var wire 1 M sampled_pressed $end
$var reg 2 N debounce_count [1:0] $end
$var reg 1 O pressed $end
$var reg 1 P pressed_pulse $end
$var reg 1 Q sync_0 $end
$var reg 1 R sync_1 $end
$upscope $end
$upscope $end
$scope module sequence_fsm_inst $end
$var wire 4 S button_pulse [3:0] $end
$var wire 1 * clk $end
$var wire 1 + rst_n $end
$var wire 3 T state_debug [2:0] $end
$var wire 2 U step_debug [1:0] $end
$var reg 1 4 display_error $end
$var reg 1 3 display_success $end
$var reg 4 V display_value [3:0] $end
$var reg 2 W input_index [1:0] $end
$var reg 4 X led_n [3:0] $end
$var reg 2 Y next_input_index [1:0] $end
$var reg 2 Z next_show_index [1:0] $end
$var reg 3 [ next_state [2:0] $end
$var reg 4 \ next_tick_count [3:0] $end
$var reg 2 ] show_index [1:0] $end
$var reg 3 ^ state [2:0] $end
$var reg 4 _ tick_count [3:0] $end
$scope function is_onehot $end
$var reg 4 ` value [3:0] $end
$upscope $end
$scope function pulse_to_index $end
$var reg 4 a value [3:0] $end
$upscope $end
$scope function sequence_at $end
$var reg 2 b index [1:0] $end
$upscope $end
$upscope $end
$scope module seven_segment_decoder_inst $end
$var wire 1 4 error $end
$var wire 1 3 success $end
$var wire 4 c value [3:0] $end
$var reg 7 d seg [6:0] $end
$upscope $end
$upscope $end
$scope task check $end
$var reg 1 e condition $end
$var reg 1024 f message [1023:0] $end
$upscope $end
$scope task do_reset $end
$upscope $end
$scope task press_button $end
$var reg 2 g index [1:0] $end
$upscope $end
$scope task press_mask $end
$var reg 4 h mask [3:0] $end
$upscope $end
$scope task test_error_in_middle $end
$upscope $end
$scope task test_error_on_first_input $end
$upscope $end
$scope task test_reset_restarts_after_error $end
$upscope $end
$scope task test_show_sequence $end
$upscope $end
$scope task test_simultaneous_buttons $end
$upscope $end
$scope task test_success_path $end
$upscope $end
$scope task wait_for_input_phase $end
$upscope $end
$scope task wait_for_state $end
$var reg 3 i target_state [2:0] $end
$var integer 32 j timeout [31:0] $end
$upscope $end
$upscope $end
$enddefinitions $end
#0
$dumpvars
bx j
bx i
bx h
bx g
bx f
xe
b111111 d
b0 c
bx b
bx a
bx `
b0 _
b0 ^
b0 ]
b0 \
b1 [
b0 Z
b0 Y
b1111 X
b0 W
b0 V
b0 U
b0 T
b0 S
1R
1Q
0P
0O
b0 N
0M
1L
1K
1J
0I
0H
b0 G
0F
1E
1D
1C
0B
0A
b0 @
0?
1>
1=
1<
0;
0:
b0 9
08
17
b0 6
b0 5
04
03
b0 2
b1111 1
b111111 0
b0 /
b0 .
b1111 -
b0 ,
0+
0*
b1111 )
b1111 (
1'
1&
1%
1$
1#
1"
0!
$end
#5000
1*
#10000
0*
#15000
1*
#20000
0*
#25000
1*
#30000
0*
#35000
0"
0#
0$
0'
b110 0
b110 d
b1 2
b1 V
b1 c
b1110 (
b1110 1
b1110 X
b0 b
b1 \
b1 /
b1 T
b1 ^
1+
1*
#40000
0*
#45000
b10 \
b1 _
1*
#50000
0*
#55000
b11 \
b10 _
b111001101101000011011110111011100100000011100110111010001100101011100000010000000110001001000000110110001101001011001110110100001110100011100110010000001001100010001010100010000110000 f
1e
b0 j
b1 i
1*
#60000
0*
#65000
b1 Z
b0 \
b11 _
1*
#70000
0*
#75000
1!
1#
1$
0%
1'
b1011011 0
b1011011 d
b1 b
b10 2
b10 V
b10 c
b1011 (
b1011 1
b1011 X
b1 \
b1 .
b1 U
b0 _
b1 ]
1*
#80000
0*
#85000
b10 \
b1 _
1*
#90000
0*
#95000
b11 \
b10 _
b111001101101000011011110111011100100000011100110111010001100101011100000010000000110010001000000110110001101001011001110110100001110100011100110010000001001100010001010100010000110010 f
1*
#100000
0*
#105000
b10 Z
b0 \
b11 _
1*
#110000
0*
#115000
0#
1%
b1001111 0
b1001111 d
b10 b
b11 2
b11 V
b11 c
b1101 (
b1101 1
b1101 X
b1 \
b10 .
b10 U
b0 _
b10 ]
1*
#120000
0*
#125000
b10 \
b1 _
1*
#130000
0*
#135000
b11 \
b10 _
b111001101101000011011110111011100100000011100110111010001100101011100000010000000110011001000000110110001101001011001110110100001110100011100110010000001001100010001010100010000110001 f
1*
#140000
0*
#145000
b11 Z
b0 \
b11 _
1*
#150000
0*
#155000
1"
0$
0'
b1100110 0
b1100110 d
b11 b
b100 2
b100 V
b100 c
b111 (
b111 1
b111 X
b1 \
b11 .
b11 U
b0 _
b11 ]
1*
#160000
0*
#165000
b10 \
b1 _
1*
#170000
0*
#175000
b11 \
b10 _
b10 i
b111001101101000011011110111011100100000011100110111010001100101011100000010000000110100001000000110110001101001011001110110100001110100011100110010000001001100010001010100010000110011 f
1*
#180000
0*
#185000
b0 Z
b10 [
b0 \
b11 _
b1 j
1*
#190000
0*
#195000
0!
1#
1$
1'
b111111 0
b111111 d
b0 2
b0 V
b0 c
b1111 (
b1111 1
b1111 X
b0 .
b0 U
b0 _
b0 ]
b10 /
b10 T
b10 ^
b10 j
1*
#200000
0*
#205000
b1 [
b0 /
b0 T
b0 ^
0+
b11000010110110001101100001000000110110001100101011001000111001100100000011011110110011001100110001000000111011101101000011010010110110001100101001000000111011101100001011010010111010001101001011011100110011100100000011001100110111101110010001000000110100101101110011100000111010101110100 f
b11 j
1*
#210000
0*
#215000
1*
#220000
0*
#225000
1*
#230000
0*
#235000
1*
#240000
0*
#245000
0"
0#
0$
0'
b110 0
b110 d
b1 2
b1 V
b1 c
b1110 (
b1110 1
b1110 X
b0 b
b1 \
b1 /
b1 T
b1 ^
1+
1*
#250000
0*
#255000
b10 \
b1 _
1*
#260000
0*
#265000
b11 \
b10 _
b0 j
1*
#270000
0*
#275000
b1 Z
b0 \
b11 _
b1 j
1*
#280000
0*
#285000
1!
1#
1$
0%
1'
b1011011 0
b1011011 d
b1 b
b10 2
b10 V
b10 c
b1011 (
b1011 1
b1011 X
b1 \
b1 .
b1 U
b0 _
b1 ]
b10 j
1*
#290000
0*
#295000
b10 \
b1 _
b11 j
1*
#300000
0*
#305000
b11 \
b10 _
b100 j
1*
#310000
0*
#315000
b10 Z
b0 \
b11 _
b101 j
1*
#320000
0*
#325000
0#
1%
b1001111 0
b1001111 d
b10 b
b11 2
b11 V
b11 c
b1101 (
b1101 1
b1101 X
b1 \
b10 .
b10 U
b0 _
b10 ]
b110 j
1*
#330000
0*
#335000
b10 \
b1 _
b111 j
1*
#340000
0*
#345000
b11 \
b10 _
b1000 j
1*
#350000
0*
#355000
b11 Z
b0 \
b11 _
b1001 j
1*
#360000
0*
#365000
1"
0$
0'
b1100110 0
b1100110 d
b11 b
b100 2
b100 V
b100 c
b111 (
b111 1
b111 X
b1 \
b11 .
b11 U
b0 _
b11 ]
b1010 j
1*
#370000
0*
#375000
b10 \
b1 _
b1011 j
1*
#380000
0*
#385000
b11 \
b10 _
b1100 j
1*
#390000
0*
#395000
b0 Z
b10 [
b0 \
b11 _
b1101 j
1*
#400000
0*
#405000
0!
1#
1$
1'
b111111 0
b111111 d
b0 2
b0 V
b0 c
b1111 (
b1111 1
b1111 X
b0 .
b0 U
b0 _
b0 ]
b10 /
b10 T
b10 ^
b1110 j
1*
#410000
0*
#415000
07
b1110 )
b1110 -
b1 h
b0 g
b11000010110110001101100001000000110110001100101011001000111001100100000011011110110011001100110001000000111011101101000011010010110110001100101001000000111011101100001011010010111010001101001011011100110011100100000011001100110111101110010001000000110100101101110011100000111010101110100 f
b1111 j
1*
#420000
0*
#425000
0<
1*
#430000
0*
#435000
18
0=
1*
#440000
0*
#445000
b1 9
1*
#450000
0*
#455000
b1 Y
b0 b
b1 a
b1 `
b0 9
b1 5
b1 S
1;
b1 6
1:
1*
#460000
0*
#465000
0"
0#
0$
0'
b110 0
b110 d
b1 2
b1 V
b1 c
b1 .
b1 U
b1 W
b0 5
b0 S
0;
1*
#470000
0*
#475000
1*
#480000
0*
#485000
1*
#490000
0*
#495000
17
b1111 )
b1111 -
1*
#500000
0*
#505000
1<
1*
#510000
0*
#515000
08
1=
1*
#520000
0*
#525000
b1 9
1*
#530000
0*
#535000
b0 9
b0 6
0:
1*
#540000
0*
#545000
1*
#550000
0*
#555000
1*
#560000
0*
#565000
1*
#570000
0*
#575000
0E
b1011 )
b1011 -
b100 h
b10 g
b1100110011010010111001001110011011101000010000001100011011011110111001001110010011001010110001101110100001000000110100101101110011100000111010101110100001000000110000101100100011101100110000101101110011000110110010101110011001000000111000001110010011011110110011101110010011001010111001101110011 f
1*
#580000
0*
#585000
0J
1*
#590000
0*
#595000
1F
0K
1*
#600000
0*
#605000
b1 G
1*
#610000
0*
#615000
b10 Y
b1 b
b100 a
b100 `
b0 G
b100 5
b100 S
1I
b100 6
1H
1*
#620000
0*
#625000
1!
1#
1$
0%
1'
b1011011 0
b1011011 d
b10 2
b10 V
b10 c
b10 .
b10 U
b10 W
b0 5
b0 S
0I
1*
#630000
0*
#635000
1*
#640000
0*
#645000
1*
#650000
0*
#655000
1E
b1111 )
b1111 -
1*
#660000
0*
#665000
1J
1*
#670000
0*
#675000
0F
1K
1*
#680000
0*
#685000
b1 G
1*
#690000
0*
#695000
b0 G
b0 6
0H
1*
#700000
0*
#705000
1*
#710000
0*
#715000
1*
#720000
0*
#725000
1*
#730000
0*
#735000
0>
b1101 )
b1101 -
b10 h
b1 g
b111001101100101011000110110111101101110011001000010000001100011011011110111001001110010011001010110001101110100001000000110100101101110011100000111010101110100001000000110000101100100011101100110000101101110011000110110010101110011001000000111000001110010011011110110011101110010011001010111001101110011 f
1*
#740000
0*
#745000
0C
1*
#750000
0*
#755000
1?
0D
1*
#760000
0*
#765000
b1 @
1*
#770000
0*
#775000
b11 Y
b10 b
b10 a
b10 `
b0 @
b10 5
b10 S
1B
b10 6
1A
1*
#780000
0*
#785000
0#
1%
b1001111 0
b1001111 d
b11 2
b11 V
b11 c
b11 .
b11 U
b11 W
b0 5
b0 S
0B
1*
#790000
0*
#795000
1*
#800000
0*
#805000
1*
#810000
0*
#815000
1>
b1111 )
b1111 -
1*
#820000
0*
#825000
1C
1*
#830000
0*
#835000
0?
1D
1*
#840000
0*
#845000
b1 @
1*
#850000
0*
#855000
b0 @
b0 6
0A
1*
#860000
0*
#865000
1*
#870000
0*
#875000
1*
#880000
0*
#885000
1*
#890000
0*
#895000
0L
b111 )
b111 -
b1000 h
b11 g
b1110100011010000110100101110010011001000010000001100011011011110111001001110010011001010110001101110100001000000110100101101110011100000111010101110100001000000110000101100100011101100110000101101110011000110110010101110011001000000111000001110010011011110110011101110010011001010111001101110011 f
1*
#900000
0*
#905000
0Q
1*
#910000
0*
#915000
1M
0R
1*
#920000
0*
#925000
b1 N
1*
#930000
0*
#935000
b100 [
b11 b
b1000 a
b1000 `
b0 N
b1000 5
b1000 S
1P
b1000 6
1O
1*
#940000
0*
#945000
1"
0&
b1101101 0
b1101101 d
13
b100 2
b100 V
b100 c
b0 .
b0 U
b100 /
b100 T
b100 ^
b0 5
b0 S
0P
1*
#950000
0*
#955000
1*
#960000
0*
#965000
1*
#970000
0*
#975000
1L
b1111 )
b1111 -
1*
#980000
0*
#985000
1Q
1*
#990000
0*
#995000
0M
1R
1*
#1000000
0*
#1005000
b1 N
1*
#1010000
0*
#1015000
b0 N
b0 6
0O
1*
#1020000
0*
#1025000
1*
#1030000
0*
#1035000
1*
#1040000
0*
#1045000
1*
#1050000
0*
#1055000
b111001101100101011101100110010101101110001000000111001101100101011001110110110101100101011011100111010000100000011100110110100001101111011101110111001100100000010100110010000001101111011011100010000001110011011101010110001101100011011001010111001101110011 f
b0 j
b100 i
1*
#1060000
0*
#1065000
1*
#1070000
0*
#1075000
1*
#1080000
0*
#1085000
1*
#1090000
0*
#1095000
1*
#1100000
0*
#1105000
1*
#1110000
0*
#1115000
1*
#1120000
0*
#1125000
1*
#1130000
0*
#1135000
1*
#1140000
0*
#1145000
1*
#1150000
0*
#1155000
0!
1#
1&
b111111 0
b111111 d
03
b0 2
b0 V
b0 c
b0 Y
b1 [
b0 W
b0 /
b0 T
b0 ^
0+
b11100110111010101100011011000110110010101110011011100110010000001110011011101000110000101110100011001010010000001101001011100110010000001101100011000010111010001100011011010000110010101100100001000000111010101101110011101000110100101101100001000000111001001100101011100110110010101110100 f
1*
#1160000
0*
#1165000
1*
#1170000
0*
#1175000
1*
#1180000
0*
#1185000
1*
#1190000
0*
#1195000
0"
0#
0$
0'
b110 0
b110 d
b1 2
b1 V
b1 c
b1110 (
b1110 1
b1110 X
b0 b
b1 \
b1 /
b1 T
b1 ^
1+
1*
#1200000
0*
#1205000
b10 \
b1 _
1*
#1210000
0*
#1215000
b11 \
b10 _
b10 i
1*
#1220000
0*
#1225000
b1 Z
b0 \
b11 _
b1 j
1*
#1230000
0*
#1235000
1!
1#
1$
0%
1'
b1011011 0
b1011011 d
b1 b
b10 2
b10 V
b10 c
b1011 (
b1011 1
b1011 X
b1 \
b1 .
b1 U
b0 _
b1 ]
b10 j
1*
#1240000
0*
#1245000
b10 \
b1 _
b11 j
1*
#1250000
0*
#1255000
b11 \
b10 _
b100 j
1*
#1260000
0*
#1265000
b10 Z
b0 \
b11 _
b101 j
1*
#1270000
0*
#1275000
0#
1%
b1001111 0
b1001111 d
b10 b
b11 2
b11 V
b11 c
b1101 (
b1101 1
b1101 X
b1 \
b10 .
b10 U
b0 _
b10 ]
b110 j
1*
#1280000
0*
#1285000
b10 \
b1 _
b111 j
1*
#1290000
0*
#1295000
b11 \
b10 _
b1000 j
1*
#1300000
0*
#1305000
b11 Z
b0 \
b11 _
b1001 j
1*
#1310000
0*
#1315000
1"
0$
0'
b1100110 0
b1100110 d
b11 b
b100 2
b100 V
b100 c
b111 (
b111 1
b111 X
b1 \
b11 .
b11 U
b0 _
b11 ]
b1010 j
1*
#1320000
0*
#1325000
b10 \
b1 _
b1011 j
1*
