dr3/tp2/gowin/src/dsp_mac.v
`timescale 1ns / 1ps

module dsp_mac #(
    parameter INPUT_WIDTH = 16,
    parameter ACC_WIDTH = 32
) (
    input wire clk,
    input wire rst_n,
    input wire clear,
    input wire valid,
    input wire [INPUT_WIDTH-1:0] a,
    input wire [INPUT_WIDTH-1:0] b,
    output reg [ACC_WIDTH-1:0] acc
);

    wire [ACC_WIDTH-1:0] product;
    assign product = a * b;

    always @(posedge clk or negedge rst_n) begin
        if (!rst_n) begin
            acc <= {ACC_WIDTH{1'b0}};
        end else if (clear) begin
            acc <= {ACC_WIDTH{1'b0}};
        end else if (valid) begin
            acc <= acc + product;
        end
    end

endmodule

dr3/tp2/sim/tb_dsp_mac.v
`timescale 1ns / 1ps

module tb_dsp_mac;

    reg clk;
    reg rst_n;
    reg clear;
    reg valid;
    reg [15:0] a;
    reg [15:0] b;
    wire [31:0] acc;
    integer errors;

    dsp_mac dut (
        .clk(clk),
        .rst_n(rst_n),
        .clear(clear),
        .valid(valid),
        .a(a),
        .b(b),
        .acc(acc)
    );

    initial begin
        clk = 1'b0;
        forever #5 clk = ~clk;
    end

    initial begin
        $dumpfile("sim/build/tb_dsp_mac.vcd");
        $dumpvars(0, tb_dsp_mac);

        errors = 0;
        rst_n = 1'b0;
        clear = 1'b0;
        valid = 1'b0;
        a = 16'd0;
        b = 16'd0;

        repeat (3) @(posedge clk);
        rst_n = 1'b1;
        repeat (1) @(posedge clk);

        clear_accumulator;
        check(acc == 32'd0, "accumulator clears to zero");

        mac_step(16'd1, 16'd1, 32'd1, "step 0 contributes 1");
        mac_step(16'd3, 16'd2, 32'd7, "step 1 contributes 6");
        mac_step(16'd2, 16'd3, 32'd13, "step 2 contributes 6");
        mac_step(16'd4, 16'd4, 32'd29, "step 3 contributes 16 and total is 29");

        if (errors == 0) begin
            $display("ALL TESTS PASSED");
            $finish;
        end else begin
            $display("TESTS FAILED: %0d error(s)", errors);
            $fatal;
        end
    end

    task check;
        input condition;
        input [1023:0] message;
        begin
            if (!condition) begin
                $display("FAIL: %0s", message);
                errors = errors + 1;
            end else begin
                $display("PASS: %0s", message);
            end
        end
    endtask

    task clear_accumulator;
        begin
            @(negedge clk);
            clear = 1'b1;
            @(posedge clk);
            @(negedge clk);
            clear = 1'b0;
        end
    endtask

    task mac_step;
        input [15:0] step_a;
        input [15:0] step_b;
        input [31:0] expected_acc;
        input [1023:0] message;
        begin
            @(negedge clk);
            valid = 1'b1;
            a = step_a;
            b = step_b;
            @(posedge clk);
            @(negedge clk);
            valid = 1'b0;
            a = 16'd0;
            b = 16'd0;
            check(acc == expected_acc, message);
        end
    endtask

endmodule

dr3/tp2/sim/build/tb_dsp_mac.vcd
$date
	Sun May  3 23:03:53 2026
$end
$version
	Icarus Verilog
$end
$timescale
	1ps
$end
$scope module tb_dsp_mac $end
$var wire 32 ! acc [31:0] $end
$var reg 16 " a [15:0] $end
$var reg 16 # b [15:0] $end
$var reg 1 $ clear $end
$var reg 1 % clk $end
$var reg 1 & rst_n $end
$var reg 1 ' valid $end
$var integer 32 ( errors [31:0] $end
$scope module dut $end
$var wire 16 ) a [15:0] $end
$var wire 16 * b [15:0] $end
$var wire 1 $ clear $end
$var wire 1 % clk $end
$var wire 1 & rst_n $end
$var wire 1 ' valid $end
$var wire 32 + product [31:0] $end
$var reg 32 , acc [31:0] $end
$upscope $end
$scope task check $end
$var reg 1 - condition $end
$var reg 1024 . message [1023:0] $end
$upscope $end
$scope task clear_accumulator $end
$upscope $end
$scope task mac_step $end
$var reg 32 / expected_acc [31:0] $end
$var reg 1024 0 message [1023:0] $end
$var reg 16 1 step_a [15:0] $end
$var reg 16 2 step_b [15:0] $end
$upscope $end
$upscope $end
$enddefinitions $end
#0
$dumpvars
bx 2
bx 1
bx 0
bx /
bx .
x-
b0 ,
b0 +
b0 *
b0 )
b0 (
0'
0&
0%
0$
b0 #
b0 "
b0 !
$end
#5000
1%
#10000
0%
#15000
1%
#20000
0%
#25000
1&
1%
#30000
0%
#35000
1%
#40000
1$
0%
#45000
1%
#50000
b111001101110100011001010111000000100000001100000010000001100011011011110110111001110100011100100110100101100010011101010111010001100101011100110010000000110001 0
b1 /
b1 2
b1 1
b110000101100011011000110111010101101101011101010110110001100001011101000110111101110010001000000110001101101100011001010110000101110010011100110010000001110100011011110010000001111010011001010111001001101111 .
1-
0$
0%
#55000
1%
#60000
b1 +
b1 #
b1 *
b1 "
b1 )
1'
0%
#65000
b1 !
b1 ,
1%
#70000
b111001101110100011001010111000000100000001100010010000001100011011011110110111001110100011100100110100101100010011101010111010001100101011100110010000000110110 0
b111 /
b10 2
b11 1
b111001101110100011001010111000000100000001100000010000001100011011011110110111001110100011100100110100101100010011101010111010001100101011100110010000000110001 .
b0 #
b0 *
b0 +
b0 "
b0 )
0'
0%
#75000
1%
#80000
b110 +
b10 #
b10 *
b11 "
b11 )
1'
0%
#85000
b111 !
b111 ,
1%
#90000
b111001101110100011001010111000000100000001100100010000001100011011011110110111001110100011100100110100101100010011101010111010001100101011100110010000000110110 0
b1101 /
b11 2
b10 1
b111001101110100011001010111000000100000001100010010000001100011011011110110111001110100011100100110100101100010011101010111010001100101011100110010000000110110 .
b0 #
b0 *
b0 +
b0 "
b0 )
0'
0%
#95000
1%
#100000
b110 +
b11 #
b11 *
b10 "
b10 )
1'
0%
#105000
b1101 !
b1101 ,
1%
#110000
b1110011011101000110010101110000001000000011001100100000011000110110111101101110011101000111001001101001011000100111010101110100011001010111001100100000001100010011011000100000011000010110111001100100001000000111010001101111011101000110000101101100001000000110100101110011001000000011001000111001 0
b11101 /
b100 2
b100 1
b111001101110100011001010111000000100000001100100010000001100011011011110110111001110100011100100110100101100010011101010111010001100101011100110010000000110110 .
b0 #
b0 *
b0 +
b0 "
b0 )
0'
0%
#115000
1%
#120000
b10000 +
b100 #
b100 *
b100 "
b100 )
1'
0%
#125000
b11101 !
b11101 ,
1%
#130000
b1110011011101000110010101110000001000000011001100100000011000110110111101101110011101000111001001101001011000100111010101110100011001010111001100100000001100010011011000100000011000010110111001100100001000000111010001101111011101000110000101101100001000000110100101110011001000000011001000111001 .
b0 #
b0 *
b0 +
b0 "
b0 )
0'
0%
