dr3/tp2/gowin/src/sync_bram.v
`timescale 1ns / 1ps

module sync_bram #(
    parameter ADDR_WIDTH = 4,
    parameter DATA_WIDTH = 16
) (
    input wire clk,
    input wire en,
    input wire we,
    input wire [ADDR_WIDTH-1:0] addr,
    input wire [DATA_WIDTH-1:0] din,
    output reg [DATA_WIDTH-1:0] dout
);

    (* syn_ramstyle = "block_ram" *)
    reg [DATA_WIDTH-1:0] mem [0:(1 << ADDR_WIDTH) - 1];

    integer index;
    initial begin
        dout = {DATA_WIDTH{1'b0}};
        for (index = 0; index < (1 << ADDR_WIDTH); index = index + 1) begin
            mem[index] = {DATA_WIDTH{1'b0}};
        end
    end

    always @(posedge clk) begin
        if (en) begin
            if (we) begin
                mem[addr] <= din;
            end
            dout <= mem[addr];
        end
    end

endmodule

dr3/tp2/sim/tb_sync_bram.v
`timescale 1ns / 1ps

module tb_sync_bram;

    reg clk;
    reg en;
    reg we;
    reg [3:0] addr;
    reg [15:0] din;
    wire [15:0] dout;
    integer errors;

    sync_bram dut (
        .clk(clk),
        .en(en),
        .we(we),
        .addr(addr),
        .din(din),
        .dout(dout)
    );

    initial begin
        clk = 1'b0;
        forever #5 clk = ~clk;
    end

    initial begin
        $dumpfile("sim/build/tb_sync_bram.vcd");
        $dumpvars(0, tb_sync_bram);

        errors = 0;
        en = 1'b0;
        we = 1'b0;
        addr = 4'd0;
        din = 16'd0;

        write_word(4'd0, 16'd1);
        write_word(4'd1, 16'd2);
        write_word(4'd8, 16'd29);

        read_word(4'd0, 16'd1, "read expected sequence slot 0");
        read_word(4'd1, 16'd2, "read expected sequence slot 1");
        read_word(4'd8, 16'd29, "read checksum slot");

        write_word(4'd1, 16'd7);
        read_word(4'd1, 16'd7, "overwrite existing slot");

        if (errors == 0) begin
            $display("ALL TESTS PASSED");
            $finish;
        end else begin
            $display("TESTS FAILED: %0d error(s)", errors);
            $fatal;
        end
    end

    task check;
        input condition;
        input [1023:0] message;
        begin
            if (!condition) begin
                $display("FAIL: %0s", message);
                errors = errors + 1;
            end else begin
                $display("PASS: %0s", message);
            end
        end
    endtask

    task write_word;
        input [3:0] write_addr;
        input [15:0] write_data;
        begin
            @(negedge clk);
            en = 1'b1;
            we = 1'b1;
            addr = write_addr;
            din = write_data;
            @(posedge clk);
            @(negedge clk);
            en = 1'b0;
            we = 1'b0;
            addr = 4'd0;
            din = 16'd0;
        end
    endtask

    task read_word;
        input [3:0] read_addr;
        input [15:0] expected_data;
        input [1023:0] message;
        begin
            @(negedge clk);
            en = 1'b1;
            we = 1'b0;
            addr = read_addr;
            @(posedge clk);
            #1;
            check(dout == expected_data, message);
            @(negedge clk);
            en = 1'b0;
            addr = 4'd0;
        end
    endtask

endmodule

dr3/tp2/sim/build/tb_sync_bram.vcd
$date
	Sun May  3 23:00:15 2026
$end
$version
	Icarus Verilog
$end
$timescale
	1ps
$end
$scope module tb_sync_bram $end
$var wire 16 ! dout [15:0] $end
$var reg 4 " addr [3:0] $end
$var reg 1 # clk $end
$var reg 16 $ din [15:0] $end
$var reg 1 % en $end
$var reg 1 & we $end
$var integer 32 ' errors [31:0] $end
$scope module dut $end
$var wire 4 ( addr [3:0] $end
$var wire 1 # clk $end
$var wire 16 ) din [15:0] $end
$var wire 1 % en $end
$var wire 1 & we $end
$var reg 16 * dout [15:0] $end
$var integer 32 + index [31:0] $end
$upscope $end
$scope task check $end
$var reg 1 , condition $end
$var reg 1024 - message [1023:0] $end
$upscope $end
$scope task read_word $end
$var reg 16 . expected_data [15:0] $end
$var reg 1024 / message [1023:0] $end
$var reg 4 0 read_addr [3:0] $end
$upscope $end
$scope task write_word $end
$var reg 4 1 write_addr [3:0] $end
$var reg 16 2 write_data [15:0] $end
$upscope $end
$upscope $end
$enddefinitions $end
#0
$dumpvars
b1 2
b0 1
bx 0
bx /
bx .
bx -
x,
b10000 +
b0 *
b0 )
b0 (
b0 '
0&
0%
b0 $
0#
b0 "
b0 !
$end
#5000
1#
#10000
b1 $
b1 )
1&
1%
0#
#15000
1#
#20000
b10 2
b1 1
b0 $
b0 )
0&
0%
0#
#25000
1#
#30000
b10 $
b10 )
b1 "
b1 (
1&
1%
0#
#35000
1#
#40000
b11101 2
b1000 1
b0 $
b0 )
b0 "
b0 (
0&
0%
0#
#45000
1#
#50000
b11101 $
b11101 )
b1000 "
b1000 (
1&
1%
0#
#55000
1#
#60000
b111001001100101011000010110010000100000011001010111100001110000011001010110001101110100011001010110010000100000011100110110010101110001011101010110010101101110011000110110010100100000011100110110110001101111011101000010000000110000 /
b1 .
b0 0
b0 $
b0 )
b0 "
b0 (
0&
0%
0#
#65000
1#
#70000
1%
0#
#75000
b1 !
b1 *
1#
#76000
b111001001100101011000010110010000100000011001010111100001110000011001010110001101110100011001010110010000100000011100110110010101110001011101010110010101101110011000110110010100100000011100110110110001101111011101000010000000110000 -
1,
#80000
b111001001100101011000010110010000100000011001010111100001110000011001010110001101110100011001010110010000100000011100110110010101110001011101010110010101101110011000110110010100100000011100110110110001101111011101000010000000110001 /
b10 .
b1 0
0%
0#
#85000
1#
#90000
b1 "
b1 (
1%
0#
#95000
b10 !
b10 *
1#
#96000
b111001001100101011000010110010000100000011001010111100001110000011001010110001101110100011001010110010000100000011100110110010101110001011101010110010101101110011000110110010100100000011100110110110001101111011101000010000000110001 -
#100000
b11100100110010101100001011001000010000001100011011010000110010101100011011010110111001101110101011011010010000001110011011011000110111101110100 /
b11101 .
b1000 0
b0 "
b0 (
0%
0#
#105000
1#
#110000
b1000 "
b1000 (
1%
0#
#115000
b11101 !
b11101 *
1#
#116000
b11100100110010101100001011001000010000001100011011010000110010101100011011010110111001101110101011011010010000001110011011011000110111101110100 -
#120000
b111 2
b1 1
b0 "
b0 (
0%
0#
#125000
1#
#130000
b111 $
b111 )
b1 "
b1 (
1&
1%
0#
#135000
b10 !
b10 *
1#
#140000
b110111101110110011001010111001001110111011100100110100101110100011001010010000001100101011110000110100101110011011101000110100101101110011001110010000001110011011011000110111101110100 /
b111 .
b1 0
b0 $
b0 )
b0 "
b0 (
0&
0%
0#
#145000
1#
#150000
b1 "
b1 (
1%
0#
#155000
b111 !
b111 *
1#
#156000
b110111101110110011001010111001001110111011100100110100101110100011001010010000001100101011110000110100101110011011101000110100101101110011001110010000001110011011011000110111101110100 -
#160000
b0 "
b0 (
0%
0#
