dr3/tp3/gowin/src/int_unsigned_alu.v
`timescale 1ns / 1ps
`default_nettype none

module int_unsigned_alu (
    input wire [1:0] op,
    input wire [7:0] a,
    input wire [7:0] b,
    output reg [7:0] result,
    output reg [5:0] flags
);

    localparam OP_ADD = 2'b00;
    localparam OP_SUB = 2'b01;
    localparam OP_MUL = 2'b10;
    localparam OP_DIV = 2'b11;

    localparam FLAG_OVERFLOW = 0;
    localparam FLAG_UNDERFLOW = 1;
    localparam FLAG_DIV_ZERO = 2;
    localparam FLAG_SATURATION = 3;
    localparam FLAG_UNSUPPORTED = 4;
    localparam FLAG_INEXACT = 5;

    reg [8:0] add_tmp;
    reg [8:0] sub_tmp;
    reg [15:0] mul_tmp;
    reg [7:0] div_tmp;
    reg [7:0] rem_tmp;

    always @* begin
        result = 8'd0;
        flags = 6'd0;
        add_tmp = 9'd0;
        sub_tmp = 9'd0;
        mul_tmp = 16'd0;
        div_tmp = 8'd0;
        rem_tmp = 8'd0;

        case (op)
            OP_ADD: begin
                add_tmp = {1'b0, a} + {1'b0, b};
                result = add_tmp[7:0];
                flags[FLAG_OVERFLOW] = add_tmp[8];
            end

            OP_SUB: begin
                sub_tmp = {1'b0, a} - {1'b0, b};
                result = sub_tmp[7:0];
                flags[FLAG_UNDERFLOW] = (a < b);
            end

            OP_MUL: begin
                mul_tmp = a * b;
                result = mul_tmp[7:0];
                flags[FLAG_OVERFLOW] = |mul_tmp[15:8];
            end

            OP_DIV: begin
                if (b == 8'd0) begin
                    result = 8'd0;
                    flags[FLAG_DIV_ZERO] = 1'b1;
                end else begin
                    div_tmp = a / b;
                    rem_tmp = a % b;
                    result = div_tmp;
                    flags[FLAG_INEXACT] = (rem_tmp != 8'd0);
                end
            end

            default: begin
                result = 8'd0;
                flags[FLAG_UNSUPPORTED] = 1'b1;
            end
        endcase

        flags[FLAG_SATURATION] = 1'b0;
    end

endmodule

`default_nettype wire

dr3/tp3/sim/tb_int_unsigned_alu.v
`timescale 1ns / 1ps

module tb_int_unsigned_alu;

    reg [1:0] op;
    reg [7:0] a;
    reg [7:0] b;
    wire [7:0] result;
    wire [5:0] flags;
    integer errors;

    int_unsigned_alu dut (
        .op(op),
        .a(a),
        .b(b),
        .result(result),
        .flags(flags)
    );

    initial begin
        $dumpfile("sim/build/tb_int_unsigned_alu.vcd");
        $dumpvars(0, tb_int_unsigned_alu);

        errors = 0;
        check_case(2'd0, 8'd12, 8'd5, 8'd17, 6'b000000, "unsigned add normal");
        check_case(2'd0, 8'd250, 8'd10, 8'd4, 6'b000001, "unsigned add overflow");
        check_case(2'd1, 8'd12, 8'd5, 8'd7, 6'b000000, "unsigned sub normal");
        check_case(2'd1, 8'd5, 8'd12, 8'd249, 6'b000010, "unsigned sub underflow");
        check_case(2'd2, 8'd12, 8'd5, 8'd60, 6'b000000, "unsigned mul normal");
        check_case(2'd2, 8'd20, 8'd20, 8'd144, 6'b000001, "unsigned mul overflow");
        check_case(2'd3, 8'd20, 8'd5, 8'd4, 6'b000000, "unsigned div exact");
        check_case(2'd3, 8'd7, 8'd2, 8'd3, 6'b100000, "unsigned div inexact");
        check_case(2'd3, 8'd7, 8'd0, 8'd0, 6'b000100, "unsigned div zero");

        finish_test;
    end

    task check_case;
        input [1:0] t_op;
        input [7:0] t_a;
        input [7:0] t_b;
        input [7:0] exp_result;
        input [5:0] exp_flags;
        input [1023:0] message;
        begin
            op = t_op;
            a = t_a;
            b = t_b;
            #1;
            if ((result !== exp_result) || (flags !== exp_flags)) begin
                $display("FAIL: %0s result=%02h expected=%02h flags=%02h expected_flags=%02h",
                    message, result, exp_result, flags, exp_flags);
                errors = errors + 1;
            end else begin
                $display("PASS: %0s", message);
            end
        end
    endtask

    task finish_test;
        begin
            if (errors == 0) begin
                $display("ALL TESTS PASSED");
                $finish;
            end else begin
                $display("TESTS FAILED: %0d error(s)", errors);
                $fatal;
            end
        end
    endtask

endmodule

dr3/tp3/sim/build/tb_int_unsigned_alu.vcd
$date
	Mon May 18 08:55:04 2026
$end
$version
	Icarus Verilog
$end
$timescale
	1ps
$end
$scope module tb_int_unsigned_alu $end
$var wire 8 ! result [7:0] $end
$var wire 6 " flags [5:0] $end
$var reg 8 # a [7:0] $end
$var reg 8 $ b [7:0] $end
$var reg 2 % op [1:0] $end
$var integer 32 & errors [31:0] $end
$scope module dut $end
$var wire 8 ' a [7:0] $end
$var wire 8 ( b [7:0] $end
$var wire 2 ) op [1:0] $end
$var reg 9 * add_tmp [8:0] $end
$var reg 8 + div_tmp [7:0] $end
$var reg 6 , flags [5:0] $end
$var reg 16 - mul_tmp [15:0] $end
$var reg 8 . rem_tmp [7:0] $end
$var reg 8 / result [7:0] $end
$var reg 9 0 sub_tmp [8:0] $end
$upscope $end
$scope task check_case $end
$var reg 6 1 exp_flags [5:0] $end
$var reg 8 2 exp_result [7:0] $end
$var reg 1024 3 message [1023:0] $end
$var reg 8 4 t_a [7:0] $end
$var reg 8 5 t_b [7:0] $end
$var reg 2 6 t_op [1:0] $end
$upscope $end
$scope task finish_test $end
$upscope $end
$upscope $end
$enddefinitions $end
#0
$dumpvars
b0 6
b101 5
b1100 4
b1110101011011100111001101101001011001110110111001100101011001000010000001100001011001000110010000100000011011100110111101110010011011010110000101101100 3
b10001 2
b0 1
b0 0
b10001 /
b0 .
b0 -
b0 ,
b0 +
b10001 *
b0 )
b101 (
b1100 '
b0 &
b0 %
b101 $
b1100 #
b0 "
b10001 !
$end
#1000
b1 "
b1 ,
b100000100 *
b100 !
b100 /
b1010 $
b1010 (
b11111010 #
b11111010 '
b11101010110111001110011011010010110011101101110011001010110010000100000011000010110010001100100001000000110111101110110011001010111001001100110011011000110111101110111 3
b1 1
b100 2
b1010 5
b11111010 4
#2000
b111 0
b0 *
b0 "
b0 ,
b111 !
b111 /
b101 $
b101 (
b1100 #
b1100 '
b1 %
b1 )
b1110101011011100111001101101001011001110110111001100101011001000010000001110011011101010110001000100000011011100110111101110010011011010110000101101100 3
b0 1
b111 2
b101 5
b1100 4
b1 6
#3000
b10 "
b10 ,
b111111001 0
b11111001 !
b11111001 /
b1100 $
b1100 (
b101 #
b101 '
b1110101011011100111001101101001011001110110111001100101011001000010000001110011011101010110001000100000011101010110111001100100011001010111001001100110011011000110111101110111 3
b10 1
b11111001 2
b1100 5
b101 4
#4000
b111100 -
b0 0
b0 "
b0 ,
b111100 !
b111100 /
b101 $
b101 (
b1100 #
b1100 '
b10 %
b10 )
b1110101011011100111001101101001011001110110111001100101011001000010000001101101011101010110110000100000011011100110111101110010011011010110000101101100 3
b0 1
b111100 2
b101 5
b1100 4
b10 6
#5000
b1 "
b1 ,
b110010000 -
b10010000 !
b10010000 /
b10100 $
b10100 (
b10100 #
b10100 '
b11101010110111001110011011010010110011101101110011001010110010000100000011011010111010101101100001000000110111101110110011001010111001001100110011011000110111101110111 3
b1 1
b10010000 2
b10100 5
b10100 4
#6000
b100 +
b0 -
b0 "
b0 ,
b100 !
b100 /
b101 $
b101 (
b11 %
b11 )
b11101010110111001110011011010010110011101101110011001010110010000100000011001000110100101110110001000000110010101111000011000010110001101110100 3
b0 1
b100 2
b101 5
b11 6
#7000
b100000 "
b100000 ,
b1 .
b11 +
b11 !
b11 /
b10 $
b10 (
b111 #
b111 '
b111010101101110011100110110100101100111011011100110010101100100001000000110010001101001011101100010000001101001011011100110010101111000011000010110001101110100 3
b100000 1
b11 2
b10 5
b111 4
#8000
b0 .
b0 +
b100 "
b100 ,
b0 !
b0 /
b0 $
b0 (
b111010101101110011100110110100101100111011011100110010101100100001000000110010001101001011101100010000001111010011001010111001001101111 3
b100 1
b0 2
b0 5
