dr3/tp3/gowin/src/fixed_q3_4_alu.v
`timescale 1ns / 1ps
`default_nettype none

module fixed_q3_4_alu (
    input wire [1:0] op,
    input wire [7:0] a,
    input wire [7:0] b,
    output reg [7:0] result,
    output reg [5:0] flags
);

    localparam OP_ADD = 2'b00;
    localparam OP_SUB = 2'b01;
    localparam OP_MUL = 2'b10;
    localparam OP_DIV = 2'b11;

    localparam FLAG_OVERFLOW = 0;
    localparam FLAG_UNDERFLOW = 1;
    localparam FLAG_DIV_ZERO = 2;
    localparam FLAG_SATURATION = 3;
    localparam FLAG_UNSUPPORTED = 4;
    localparam FLAG_INEXACT = 5;

    localparam signed [15:0] Q_MAX = 16'sd127;
    localparam signed [15:0] Q_MIN = -16'sd128;

    wire signed [7:0] a_s;
    wire signed [7:0] b_s;

    reg signed [15:0] tmp;
    reg signed [15:0] shifted;
    reg signed [15:0] dividend;
    reg signed [15:0] divisor;
    reg signed [15:0] quotient;
    reg signed [15:0] remainder;
    reg signed [15:0] saturated;
    reg [3:0] lost_bits;

    assign a_s = a;
    assign b_s = b;

    always @* begin
        result = 8'd0;
        flags = 6'd0;
        tmp = 16'sd0;
        shifted = 16'sd0;
        dividend = 16'sd0;
        divisor = 16'sd0;
        quotient = 16'sd0;
        remainder = 16'sd0;
        saturated = 16'sd0;
        lost_bits = 4'd0;

        case (op)
            OP_ADD: begin
                tmp = {{8{a_s[7]}}, a_s} + {{8{b_s[7]}}, b_s};
                saturated = tmp;
                if (tmp > Q_MAX) begin
                    saturated = Q_MAX;
                    flags[FLAG_OVERFLOW] = 1'b1;
                    flags[FLAG_SATURATION] = 1'b1;
                end else if (tmp < Q_MIN) begin
                    saturated = Q_MIN;
                    flags[FLAG_UNDERFLOW] = 1'b1;
                    flags[FLAG_SATURATION] = 1'b1;
                end
                result = saturated[7:0];
            end

            OP_SUB: begin
                tmp = {{8{a_s[7]}}, a_s} - {{8{b_s[7]}}, b_s};
                saturated = tmp;
                if (tmp > Q_MAX) begin
                    saturated = Q_MAX;
                    flags[FLAG_OVERFLOW] = 1'b1;
                    flags[FLAG_SATURATION] = 1'b1;
                end else if (tmp < Q_MIN) begin
                    saturated = Q_MIN;
                    flags[FLAG_UNDERFLOW] = 1'b1;
                    flags[FLAG_SATURATION] = 1'b1;
                end
                result = saturated[7:0];
            end

            OP_MUL: begin
                tmp = a_s * b_s;
                lost_bits = tmp[3:0];
                shifted = tmp >>> 4;
                saturated = shifted;
                flags[FLAG_INEXACT] = (lost_bits != 4'd0);
                if (shifted > Q_MAX) begin
                    saturated = Q_MAX;
                    flags[FLAG_OVERFLOW] = 1'b1;
                    flags[FLAG_SATURATION] = 1'b1;
                end else if (shifted < Q_MIN) begin
                    saturated = Q_MIN;
                    flags[FLAG_UNDERFLOW] = 1'b1;
                    flags[FLAG_SATURATION] = 1'b1;
                end
                result = saturated[7:0];
            end

            OP_DIV: begin
                if (b_s == 8'sd0) begin
                    result = 8'd0;
                    flags[FLAG_DIV_ZERO] = 1'b1;
                end else begin
                    dividend = {{8{a_s[7]}}, a_s} <<< 4;
                    divisor = {{8{b_s[7]}}, b_s};
                    quotient = dividend / divisor;
                    remainder = dividend % divisor;
                    saturated = quotient;
                    flags[FLAG_INEXACT] = (remainder != 16'sd0);
                    if (quotient > Q_MAX) begin
                        saturated = Q_MAX;
                        flags[FLAG_OVERFLOW] = 1'b1;
                        flags[FLAG_SATURATION] = 1'b1;
                    end else if (quotient < Q_MIN) begin
                        saturated = Q_MIN;
                        flags[FLAG_UNDERFLOW] = 1'b1;
                        flags[FLAG_SATURATION] = 1'b1;
                    end
                    result = saturated[7:0];
                end
            end

            default: begin
                result = 8'd0;
                flags[FLAG_UNSUPPORTED] = 1'b1;
            end
        endcase
    end

endmodule

`default_nettype wire

dr3/tp3/sim/tb_fixed_q3_4_alu.v
`timescale 1ns / 1ps

module tb_fixed_q3_4_alu;

    reg [1:0] op;
    reg [7:0] a;
    reg [7:0] b;
    wire [7:0] result;
    wire [5:0] flags;
    integer errors;

    fixed_q3_4_alu dut (
        .op(op),
        .a(a),
        .b(b),
        .result(result),
        .flags(flags)
    );

    initial begin
        $dumpfile("sim/build/tb_fixed_q3_4_alu.vcd");
        $dumpvars(0, tb_fixed_q3_4_alu);

        errors = 0;
        check_case(2'd0, 8'd24, 8'd8, 8'd32, 6'b000000, "fixed add 1.5 + 0.5");
        check_case(2'd0, 8'd120, 8'd16, 8'd127, 6'b001001, "fixed add positive saturation");
        check_case(2'd0, 8'h88, 8'hf0, 8'h80, 6'b001010, "fixed add negative saturation");
        check_case(2'd1, 8'd24, 8'd8, 8'd16, 6'b000000, "fixed sub 1.5 - 0.5");
        check_case(2'd1, 8'h88, 8'd16, 8'h80, 6'b001010, "fixed sub negative saturation");
        check_case(2'd1, 8'd120, 8'hf0, 8'd127, 6'b001001, "fixed sub positive saturation");
        check_case(2'd2, 8'd24, 8'd8, 8'd12, 6'b000000, "fixed mul exact");
        check_case(2'd2, 8'd120, 8'd32, 8'd127, 6'b001001, "fixed mul positive saturation");
        check_case(2'd2, 8'h88, 8'd32, 8'h80, 6'b001010, "fixed mul negative saturation");
        check_case(2'd2, 8'd5, 8'd5, 8'd1, 6'b100000, "fixed mul truncation");
        check_case(2'd3, 8'd24, 8'd8, 8'd48, 6'b000000, "fixed div exact");
        check_case(2'd3, 8'd16, 8'd48, 8'd5, 6'b100000, "fixed div truncation");
        check_case(2'd3, 8'h80, 8'd8, 8'h80, 6'b001010, "fixed div negative saturation");
        check_case(2'd3, 8'd16, 8'd0, 8'd0, 6'b000100, "fixed div zero");

        finish_test;
    end

    task check_case;
        input [1:0] t_op;
        input [7:0] t_a;
        input [7:0] t_b;
        input [7:0] exp_result;
        input [5:0] exp_flags;
        input [1023:0] message;
        begin
            op = t_op;
            a = t_a;
            b = t_b;
            #1;
            if ((result !== exp_result) || (flags !== exp_flags)) begin
                $display("FAIL: %0s result=%02h expected=%02h flags=%02h expected_flags=%02h",
                    message, result, exp_result, flags, exp_flags);
                errors = errors + 1;
            end else begin
                $display("PASS: %0s", message);
            end
        end
    endtask

    task finish_test;
        begin
            if (errors == 0) begin
                $display("ALL TESTS PASSED");
                $finish;
            end else begin
                $display("TESTS FAILED: %0d error(s)", errors);
                $fatal;
            end
        end
    endtask

endmodule

dr3/tp3/evidencias/simulacao/tb_fixed_q3_4_alu.vcd
$date
	Mon May 18 08:55:04 2026
$end
$version
	Icarus Verilog
$end
$timescale
	1ps
$end
$scope module tb_fixed_q3_4_alu $end
$var wire 8 ! result [7:0] $end
$var wire 6 " flags [5:0] $end
$var reg 8 # a [7:0] $end
$var reg 8 $ b [7:0] $end
$var reg 2 % op [1:0] $end
$var integer 32 & errors [31:0] $end
$scope module dut $end
$var wire 8 ' a [7:0] $end
$var wire 8 ( a_s [7:0] $end
$var wire 8 ) b [7:0] $end
$var wire 8 * b_s [7:0] $end
$var wire 2 + op [1:0] $end
$var reg 16 , dividend [15:0] $end
$var reg 16 - divisor [15:0] $end
$var reg 6 . flags [5:0] $end
$var reg 4 / lost_bits [3:0] $end
$var reg 16 0 quotient [15:0] $end
$var reg 16 1 remainder [15:0] $end
$var reg 8 2 result [7:0] $end
$var reg 16 3 saturated [15:0] $end
$var reg 16 4 shifted [15:0] $end
$var reg 16 5 tmp [15:0] $end
$upscope $end
$scope task check_case $end
$var reg 6 6 exp_flags [5:0] $end
$var reg 8 7 exp_result [7:0] $end
$var reg 1024 8 message [1023:0] $end
$var reg 8 9 t_a [7:0] $end
$var reg 8 : t_b [7:0] $end
$var reg 2 ; t_op [1:0] $end
$upscope $end
$scope task finish_test $end
$upscope $end
$upscope $end
$enddefinitions $end
#0
$dumpvars
b0 ;
b1000 :
b11000 9
b1100110011010010111100001100101011001000010000001100001011001000110010000100000001100010010111000110101001000000010101100100000001100000010111000110101 8
b100000 7
b0 6
b100000 5
b0 4
b100000 3
b100000 2
b0 1
b0 0
b0 /
b0 .
b0 -
b0 ,
b0 +
b1000 *
b1000 )
b11000 (
b11000 '
b0 &
b0 %
b1000 $
b11000 #
b0 "
b100000 !
$end
#1000
b1001 "
b1001 .
b1111111 3
b10001000 5
b1111111 !
b1111111 2
b10000 *
b10000 $
b10000 )
b1111000 (
b1111000 #
b1111000 '
b110011001101001011110000110010101100100001000000110000101100100011001000010000001110000011011110111001101101001011101000110100101110110011001010010000001110011011000010111010001110101011100100110000101110100011010010110111101101110 8
b1001 6
b1111111 7
b10000 :
b1111000 9
#2000
b1111111110000000 3
b1111111101111000 5
b1010 "
b1010 .
b10000000 !
b10000000 2
b11110000 *
b11110000 $
b11110000 )
b10001000 (
b10001000 #
b10001000 '
b110011001101001011110000110010101100100001000000110000101100100011001000010000001101110011001010110011101100001011101000110100101110110011001010010000001110011011000010111010001110101011100100110000101110100011010010110111101101110 8
b1010 6
b10000000 7
b11110000 :
b10001000 9
#3000
b10000 3
b10000 5
b0 "
b0 .
b10000 !
b10000 2
b1000 *
b1000 $
b1000 )
b11000 (
b11000 #
b11000 '
b1 %
b1 +
b1100110011010010111100001100101011001000010000001110011011101010110001000100000001100010010111000110101001000000010110100100000001100000010111000110101 8
b0 6
b10000 7
b1000 :
b11000 9
b1 ;
#4000
b1010 "
b1010 .
b1111111110000000 3
b1111111101111000 5
b10000000 !
b10000000 2
b10000 *
b10000 $
b10000 )
b10001000 (
b10001000 #
b10001000 '
b110011001101001011110000110010101100100001000000111001101110101011000100010000001101110011001010110011101100001011101000110100101110110011001010010000001110011011000010111010001110101011100100110000101110100011010010110111101101110 8
b1010 6
b10000000 7
b10000 :
b10001000 9
#5000
b1111111 3
b10001000 5
b1001 "
b1001 .
b1111111 !
b1111111 2
b11110000 *
b11110000 $
b11110000 )
b1111000 (
b1111000 #
b1111000 '
b110011001101001011110000110010101100100001000000111001101110101011000100010000001110000011011110111001101101001011101000110100101110110011001010010000001110011011000010111010001110101011100100110000101110100011010010110111101101110 8
b1001 6
b1111111 7
b11110000 :
b1111000 9
#6000
b1100 4
b1100 3
b11000000 5
b0 "
b0 .
b1100 !
b1100 2
b1000 *
b1000 $
b1000 )
b11000 (
b11000 #
b11000 '
b10 %
b10 +
b11001100110100101111000011001010110010000100000011011010111010101101100001000000110010101111000011000010110001101110100 8
b0 6
b1100 7
b1000 :
b11000 9
b10 ;
#7000
b1001 "
b1001 .
b1111111 3
b11110000 4
b111100000000 5
b1111111 !
b1111111 2
b100000 *
b100000 $
b100000 )
b1111000 (
b1111000 #
b1111000 '
b110011001101001011110000110010101100100001000000110110101110101011011000010000001110000011011110111001101101001011101000110100101110110011001010010000001110011011000010111010001110101011100100110000101110100011010010110111101101110 8
b1001 6
b1111111 7
b100000 :
b1111000 9
#8000
b1111111110000000 3
b1111111100010000 4
b1111000100000000 5
b1010 "
b1010 .
b10000000 !
b10000000 2
b10001000 (
b10001000 #
b10001000 '
b110011001101001011110000110010101100100001000000110110101110101011011000010000001101110011001010110011101100001011101000110100101110110011001010010000001110011011000010111010001110101011100100110000101110100011010010110111101101110 8
b1010 6
b10000000 7
b10001000 9
#9000
b1001 /
b1 3
b1 4
b11001 5
b100000 "
b100000 .
b1 !
b1 2
b101 *
b101 $
b101 )
b101 (
b101 #
b101 '
b110011001101001011110000110010101100100001000000110110101110101011011000010000001110100011100100111010101101110011000110110000101110100011010010110111101101110 8
b100000 6
b1 7
b101 :
b101 9
#10000
b110000 0
b1000 -
b110000000 ,
b0 /
b110000 3
b0 4
b0 5
b0 "
b0 .
b110000 !
b110000 2
b1000 *
b1000 $
b1000 )
b11000 (
b11000 #
b11000 '
b11 %
b11 +
b11001100110100101111000011001010110010000100000011001000110100101110110001000000110010101111000011000010110001101110100 8
b0 6
b110000 7
b1000 :
b11000 9
b11 ;
#11000
b100000 "
b100000 .
b10000 1
b101 3
b101 0
b110000 -
b100000000 ,
b101 !
b101 2
b110000 *
b110000 $
b110000 )
b10000 (
b10000 #
b10000 '
b110011001101001011110000110010101100100001000000110010001101001011101100010000001110100011100100111010101101110011000110110000101110100011010010110111101101110 8
b100000 6
b101 7
b110000 :
b10000 9
#12000
b1111111110000000 3
b0 1
b1111111100000000 0
b1000 -
b1111100000000000 ,
b1010 "
b1010 .
b10000000 !
b10000000 2
b1000 *
b1000 $
b1000 )
b10000000 (
b10000000 #
b10000000 '
b110011001101001011110000110010101100100001000000110010001101001011101100010000001101110011001010110011101100001011101000110100101110110011001010010000001110011011000010111010001110101011100100110000101110100011010010110111101101110 8
b1010 6
b10000000 7
b1000 :
b10000000 9
#13000
b0 3
b0 0
b0 -
b0 ,
b100 "
b100 .
b0 !
b0 2
b0 *
b0 $
b0 )
b10000 (
b10000 #
b10000 '
b110011001101001011110000110010101100100001000000110010001101001011101100010000001111010011001010111001001101111 8
b100 6
b0 7
b0 :
b10000 9
