dr3/tp3/gowin/src/int_signed_alu.v
`timescale 1ns / 1ps
`default_nettype none

module int_signed_alu (
    input wire [1:0] op,
    input wire [7:0] a,
    input wire [7:0] b,
    output reg [7:0] result,
    output reg [5:0] flags
);

    localparam OP_ADD = 2'b00;
    localparam OP_SUB = 2'b01;
    localparam OP_MUL = 2'b10;
    localparam OP_DIV = 2'b11;

    localparam FLAG_OVERFLOW = 0;
    localparam FLAG_UNDERFLOW = 1;
    localparam FLAG_DIV_ZERO = 2;
    localparam FLAG_SATURATION = 3;
    localparam FLAG_UNSUPPORTED = 4;
    localparam FLAG_INEXACT = 5;

    wire signed [7:0] a_s;
    wire signed [7:0] b_s;

    reg signed [8:0] addsub_tmp;
    reg signed [15:0] mul_tmp;
    reg signed [7:0] div_tmp;
    reg signed [7:0] rem_tmp;

    assign a_s = a;
    assign b_s = b;

    always @* begin
        result = 8'd0;
        flags = 6'd0;
        addsub_tmp = 9'sd0;
        mul_tmp = 16'sd0;
        div_tmp = 8'sd0;
        rem_tmp = 8'sd0;

        case (op)
            OP_ADD: begin
                addsub_tmp = {a_s[7], a_s} + {b_s[7], b_s};
                result = addsub_tmp[7:0];
                flags[FLAG_OVERFLOW] = (addsub_tmp > 9'sd127);
                flags[FLAG_UNDERFLOW] = (addsub_tmp < -9'sd128);
            end

            OP_SUB: begin
                addsub_tmp = {a_s[7], a_s} - {b_s[7], b_s};
                result = addsub_tmp[7:0];
                flags[FLAG_OVERFLOW] = (addsub_tmp > 9'sd127);
                flags[FLAG_UNDERFLOW] = (addsub_tmp < -9'sd128);
            end

            OP_MUL: begin
                mul_tmp = a_s * b_s;
                result = mul_tmp[7:0];
                flags[FLAG_OVERFLOW] = (mul_tmp > 16'sd127);
                flags[FLAG_UNDERFLOW] = (mul_tmp < -16'sd128);
            end

            OP_DIV: begin
                if (b_s == 8'sd0) begin
                    result = 8'd0;
                    flags[FLAG_DIV_ZERO] = 1'b1;
                end else if ((a_s == -8'sd128) && (b_s == -8'sd1)) begin
                    result = 8'h80;
                    flags[FLAG_OVERFLOW] = 1'b1;
                end else begin
                    div_tmp = a_s / b_s;
                    rem_tmp = a_s % b_s;
                    result = div_tmp;
                    flags[FLAG_INEXACT] = (rem_tmp != 8'sd0);
                end
            end

            default: begin
                result = 8'd0;
                flags[FLAG_UNSUPPORTED] = 1'b1;
            end
        endcase

        flags[FLAG_SATURATION] = 1'b0;
    end

endmodule

`default_nettype wire

dr3/tp3/sim/tb_int_signed_alu.v
`timescale 1ns / 1ps

module tb_int_signed_alu;

    reg [1:0] op;
    reg [7:0] a;
    reg [7:0] b;
    wire [7:0] result;
    wire [5:0] flags;
    integer errors;

    int_signed_alu dut (
        .op(op),
        .a(a),
        .b(b),
        .result(result),
        .flags(flags)
    );

    initial begin
        $dumpfile("sim/build/tb_int_signed_alu.vcd");
        $dumpvars(0, tb_int_signed_alu);

        errors = 0;
        check_case(2'd0, 8'd10, 8'd5, 8'd15, 6'b000000, "signed add normal");
        check_case(2'd0, 8'd100, 8'd40, 8'd140, 6'b000001, "signed add positive overflow");
        check_case(2'd0, 8'hce, 8'hb0, 8'd126, 6'b000010, "signed add negative underflow");
        check_case(2'd1, 8'd10, 8'd5, 8'd5, 6'b000000, "signed sub normal");
        check_case(2'd1, 8'h9c, 8'd40, 8'd116, 6'b000010, "signed sub negative underflow");
        check_case(2'd1, 8'd100, 8'hd8, 8'd140, 6'b000001, "signed sub positive overflow");
        check_case(2'd2, 8'hfc, 8'd6, 8'he8, 6'b000000, "signed mul normal");
        check_case(2'd2, 8'd50, 8'd5, 8'hfa, 6'b000001, "signed mul overflow");
        check_case(2'd2, 8'hc4, 8'd3, 8'd76, 6'b000010, "signed mul underflow");
        check_case(2'd3, 8'hec, 8'd5, 8'hfc, 6'b000000, "signed div exact");
        check_case(2'd3, 8'd7, 8'd2, 8'd3, 6'b100000, "signed div inexact");
        check_case(2'd3, 8'hf9, 8'd2, 8'hfd, 6'b100000, "signed negative div inexact");
        check_case(2'd3, 8'd7, 8'd0, 8'd0, 6'b000100, "signed div zero");
        check_case(2'd3, 8'h80, 8'hff, 8'h80, 6'b000001, "signed min divided by minus one overflow");

        finish_test;
    end

    task check_case;
        input [1:0] t_op;
        input [7:0] t_a;
        input [7:0] t_b;
        input [7:0] exp_result;
        input [5:0] exp_flags;
        input [1023:0] message;
        begin
            op = t_op;
            a = t_a;
            b = t_b;
            #1;
            if ((result !== exp_result) || (flags !== exp_flags)) begin
                $display("FAIL: %0s result=%02h expected=%02h flags=%02h expected_flags=%02h",
                    message, result, exp_result, flags, exp_flags);
                errors = errors + 1;
            end else begin
                $display("PASS: %0s", message);
            end
        end
    endtask

    task finish_test;
        begin
            if (errors == 0) begin
                $display("ALL TESTS PASSED");
                $finish;
            end else begin
                $display("TESTS FAILED: %0d error(s)", errors);
                $fatal;
            end
        end
    endtask

endmodule

dr3/tp3/evidencias/simulacao/tb_int_signed_alu.vcd
$date
	Mon May 18 08:55:04 2026
$end
$version
	Icarus Verilog
$end
$timescale
	1ps
$end
$scope module tb_int_signed_alu $end
$var wire 8 ! result [7:0] $end
$var wire 6 " flags [5:0] $end
$var reg 8 # a [7:0] $end
$var reg 8 $ b [7:0] $end
$var reg 2 % op [1:0] $end
$var integer 32 & errors [31:0] $end
$scope module dut $end
$var wire 8 ' a [7:0] $end
$var wire 8 ( a_s [7:0] $end
$var wire 8 ) b [7:0] $end
$var wire 8 * b_s [7:0] $end
$var wire 2 + op [1:0] $end
$var reg 9 , addsub_tmp [8:0] $end
$var reg 8 - div_tmp [7:0] $end
$var reg 6 . flags [5:0] $end
$var reg 16 / mul_tmp [15:0] $end
$var reg 8 0 rem_tmp [7:0] $end
$var reg 8 1 result [7:0] $end
$upscope $end
$scope task check_case $end
$var reg 6 2 exp_flags [5:0] $end
$var reg 8 3 exp_result [7:0] $end
$var reg 1024 4 message [1023:0] $end
$var reg 8 5 t_a [7:0] $end
$var reg 8 6 t_b [7:0] $end
$var reg 2 7 t_op [1:0] $end
$upscope $end
$scope task finish_test $end
$upscope $end
$upscope $end
$enddefinitions $end
#0
$dumpvars
b0 7
b101 6
b1010 5
b111001101101001011001110110111001100101011001000010000001100001011001000110010000100000011011100110111101110010011011010110000101101100 4
b1111 3
b0 2
b1111 1
b0 0
b0 /
b0 .
b0 -
b1111 ,
b0 +
b101 *
b101 )
b1010 (
b1010 '
b0 &
b0 %
b101 $
b1010 #
b0 "
b1111 !
$end
#1000
b1 "
b1 .
b10001100 ,
b10001100 !
b10001100 1
b101000 *
b101000 $
b101000 )
b1100100 (
b1100100 #
b1100100 '
b1110011011010010110011101101110011001010110010000100000011000010110010001100100001000000111000001101111011100110110100101110100011010010111011001100101001000000110111101110110011001010111001001100110011011000110111101110111 4
b1 2
b10001100 3
b101000 6
b1100100 5
#2000
b101111110 ,
b10 "
b10 .
b1111110 !
b1111110 1
b10110000 *
b10110000 $
b10110000 )
b11001110 (
b11001110 #
b11001110 '
b111001101101001011001110110111001100101011001000010000001100001011001000110010000100000011011100110010101100111011000010111010001101001011101100110010100100000011101010110111001100100011001010111001001100110011011000110111101110111 4
b10 2
b1111110 3
b10110000 6
b11001110 5
#3000
b101 ,
b0 "
b0 .
b101 !
b101 1
b101 *
b101 $
b101 )
b1010 (
b1010 #
b1010 '
b1 %
b1 +
b111001101101001011001110110111001100101011001000010000001110011011101010110001000100000011011100110111101110010011011010110000101101100 4
b0 2
b101 3
b101 6
b1010 5
b1 7
#4000
b10 "
b10 .
b101110100 ,
b1110100 !
b1110100 1
b101000 *
b101000 $
b101000 )
b10011100 (
b10011100 #
b10011100 '
b111001101101001011001110110111001100101011001000010000001110011011101010110001000100000011011100110010101100111011000010111010001101001011101100110010100100000011101010110111001100100011001010111001001100110011011000110111101110111 4
b10 2
b1110100 3
b101000 6
b10011100 5
#5000
b10001100 ,
b1 "
b1 .
b10001100 !
b10001100 1
b11011000 *
b11011000 $
b11011000 )
b1100100 (
b1100100 #
b1100100 '
b1110011011010010110011101101110011001010110010000100000011100110111010101100010001000000111000001101111011100110110100101110100011010010111011001100101001000000110111101110110011001010111001001100110011011000110111101110111 4
b1 2
b10001100 3
b11011000 6
b1100100 5
#6000
b1111111111101000 /
b0 ,
b0 "
b0 .
b11101000 !
b11101000 1
b110 *
b110 $
b110 )
b11111100 (
b11111100 #
b11111100 '
b10 %
b10 +
b111001101101001011001110110111001100101011001000010000001101101011101010110110000100000011011100110111101110010011011010110000101101100 4
b0 2
b11101000 3
b110 6
b11111100 5
b10 7
#7000
b1 "
b1 .
b11111010 /
b11111010 !
b11111010 1
b101 *
b101 $
b101 )
b110010 (
b110010 #
b110010 '
b1110011011010010110011101101110011001010110010000100000011011010111010101101100001000000110111101110110011001010111001001100110011011000110111101110111 4
b1 2
b11111010 3
b101 6
b110010 5
#8000
b1111111101001100 /
b10 "
b10 .
b1001100 !
b1001100 1
b11 *
b11 $
b11 )
b11000100 (
b11000100 #
b11000100 '
b111001101101001011001110110111001100101011001000010000001101101011101010110110000100000011101010110111001100100011001010111001001100110011011000110111101110111 4
b10 2
b1001100 3
b11 6
b11000100 5
#9000
b11111100 -
b0 /
b0 "
b0 .
b11111100 !
b11111100 1
b101 *
b101 $
b101 )
b11101100 (
b11101100 #
b11101100 '
b11 %
b11 +
b1110011011010010110011101101110011001010110010000100000011001000110100101110110001000000110010101111000011000010110001101110100 4
b0 2
b11111100 3
b101 6
b11101100 5
b11 7
#10000
b100000 "
b100000 .
b1 0
b11 -
b11 !
b11 1
b10 *
b10 $
b10 )
b111 (
b111 #
b111 '
b11100110110100101100111011011100110010101100100001000000110010001101001011101100010000001101001011011100110010101111000011000010110001101110100 4
b100000 2
b11 3
b10 6
b111 5
#11000
b11111111 0
b11111101 -
b100000 "
b100000 .
b11111101 !
b11111101 1
b11111001 (
b11111001 #
b11111001 '
b11100110110100101100111011011100110010101100100001000000110111001100101011001110110000101110100011010010111011001100101001000000110010001101001011101100010000001101001011011100110010101111000011000010110001101110100 4
b11111101 3
b11111001 5
#12000
b0 0
b0 -
b100 "
b100 .
b0 !
b0 1
b0 *
b0 $
b0 )
b111 (
b111 #
b111 '
b11100110110100101100111011011100110010101100100001000000110010001101001011101100010000001111010011001010111001001101111 4
b100 2
b0 3
b0 6
b111 5
#13000
b10000000 !
b10000000 1
b1 "
b1 .
b11111111 *
b11111111 $
b11111111 )
b10000000 (
b10000000 #
b10000000 '
b1110011011010010110011101101110011001010110010000100000011011010110100101101110001000000110010001101001011101100110100101100100011001010110010000100000011000100111100100100000011011010110100101101110011101010111001100100000011011110110111001100101001000000110111101110110011001010111001001100110011011000110111101110111 4
b1 2
b10000000 3
b11111111 6
b10000000 5
