dr3/tp3/gowin/src/minifloat_e4m3_addsub.v
`timescale 1ns / 1ps
`default_nettype none

module minifloat_e4m3_addsub (
    input wire op_sub,
    input wire [7:0] a,
    input wire [7:0] b,
    output reg [7:0] result,
    output reg [5:0] flags
);

    localparam FLAG_OVERFLOW = 0;
    localparam FLAG_UNDERFLOW = 1;
    localparam FLAG_DIV_ZERO = 2;
    localparam FLAG_SATURATION = 3;
    localparam FLAG_UNSUPPORTED = 4;
    localparam FLAG_INEXACT = 5;

    localparam [3:0] EXP_INF = 4'hf;
    localparam [19:0] MIN_NORMAL_MAG = 20'd2048;
    localparam [19:0] NEXT_EXP_MAG = 20'd4096;

    reg sign_a;
    reg sign_b;
    reg sign_b_eff;
    reg sign_res;
    reg [3:0] exp_a;
    reg [3:0] exp_b;
    reg [3:0] exp_work;
    reg [3:0] frac_a;
    reg [3:0] frac_b;
    reg [4:0] exp_diff;
    reg [19:0] mag_a;
    reg [19:0] mag_b;
    reg [19:0] aligned_a;
    reg [19:0] aligned_b;
    reg [20:0] shifted_pack;
    reg signed [21:0] signed_a;
    reg signed [21:0] signed_b;
    reg signed [21:0] sum_signed;
    reg [21:0] abs_sum;
    reg [19:0] mag_work;
    reg sticky;
    integer norm_i;

    function [20:0] shift_right_sticky;
        input [19:0] value;
        input [4:0] amount;
        reg [19:0] mask;
        begin
            if (amount == 5'd0) begin
                shift_right_sticky = {1'b0, value};
            end else if (amount >= 5'd20) begin
                shift_right_sticky = {|value, 20'd0};
            end else begin
                mask = (20'd1 << amount) - 20'd1;
                shift_right_sticky = {|(value & mask), value >> amount};
            end
        end
    endfunction

    always @* begin
        result = 8'd0;
        flags = 6'd0;

        sign_a = a[7];
        sign_b = b[7];
        sign_b_eff = b[7] ^ op_sub;
        sign_res = 1'b0;
        exp_a = a[6:3];
        exp_b = b[6:3];
        exp_work = 4'd0;
        frac_a = {1'b1, a[2:0]};
        frac_b = {1'b1, b[2:0]};
        exp_diff = 5'd0;
        mag_a = 20'd0;
        mag_b = 20'd0;
        aligned_a = 20'd0;
        aligned_b = 20'd0;
        shifted_pack = 21'd0;
        signed_a = 22'sd0;
        signed_b = 22'sd0;
        sum_signed = 22'sd0;
        abs_sum = 22'd0;
        mag_work = 20'd0;
        sticky = 1'b0;
        norm_i = 0;

        if ((exp_a == EXP_INF) && (a[2:0] != 3'd0)) begin
            result = 8'h7f;
            flags[FLAG_OVERFLOW] = 1'b1;
            flags[FLAG_INEXACT] = 1'b1;
        end else if ((exp_b == EXP_INF) && (b[2:0] != 3'd0)) begin
            result = 8'h7f;
            flags[FLAG_OVERFLOW] = 1'b1;
            flags[FLAG_INEXACT] = 1'b1;
        end else if ((exp_a == EXP_INF) && (exp_b == EXP_INF) && (sign_a != sign_b_eff)) begin
            result = 8'h7f;
            flags[FLAG_OVERFLOW] = 1'b1;
            flags[FLAG_INEXACT] = 1'b1;
        end else if (exp_a == EXP_INF) begin
            result = {sign_a, EXP_INF, 3'd0};
            flags[FLAG_OVERFLOW] = 1'b1;
        end else if (exp_b == EXP_INF) begin
            result = {sign_b_eff, EXP_INF, 3'd0};
            flags[FLAG_OVERFLOW] = 1'b1;
        end else if ((exp_a == 4'd0) && (a[2:0] == 3'd0) && (exp_b == 4'd0) && (b[2:0] == 3'd0)) begin
            result = 8'd0;
        end else if ((exp_a == 4'd0) && (a[2:0] == 3'd0)) begin
            if (exp_b == 4'd0) begin
                result = 8'd0;
                flags[FLAG_UNDERFLOW] = (b[2:0] != 3'd0);
                flags[FLAG_INEXACT] = (b[2:0] != 3'd0);
            end else begin
                result = {sign_b_eff, exp_b, b[2:0]};
            end
        end else if ((exp_b == 4'd0) && (b[2:0] == 3'd0)) begin
            if (exp_a == 4'd0) begin
                result = 8'd0;
                flags[FLAG_UNDERFLOW] = (a[2:0] != 3'd0);
                flags[FLAG_INEXACT] = (a[2:0] != 3'd0);
            end else begin
                result = a;
            end
        end else if ((exp_a == 4'd0) || (exp_b == 4'd0)) begin
            result = 8'd0;
            flags[FLAG_UNDERFLOW] = 1'b1;
            flags[FLAG_INEXACT] = 1'b1;
        end else begin
            mag_a = {8'd0, frac_a, 8'd0};
            mag_b = {8'd0, frac_b, 8'd0};

            if (exp_a >= exp_b) begin
                exp_work = exp_a;
                exp_diff = {1'b0, exp_a} - {1'b0, exp_b};
                aligned_a = mag_a;
                shifted_pack = shift_right_sticky(mag_b, exp_diff);
                aligned_b = shifted_pack[19:0];
                sticky = shifted_pack[20];
            end else begin
                exp_work = exp_b;
                exp_diff = {1'b0, exp_b} - {1'b0, exp_a};
                aligned_b = mag_b;
                shifted_pack = shift_right_sticky(mag_a, exp_diff);
                aligned_a = shifted_pack[19:0];
                sticky = shifted_pack[20];
            end

            signed_a = sign_a ? -$signed({2'b00, aligned_a}) : $signed({2'b00, aligned_a});
            signed_b = sign_b_eff ? -$signed({2'b00, aligned_b}) : $signed({2'b00, aligned_b});
            sum_signed = signed_a + signed_b;

            if (sum_signed == 22'sd0) begin
                result = 8'd0;
                flags[FLAG_INEXACT] = sticky;
            end else begin
                sign_res = sum_signed[21];
                abs_sum = sign_res ? -sum_signed : sum_signed;
                mag_work = abs_sum[19:0];

                for (norm_i = 0; norm_i < 5; norm_i = norm_i + 1) begin
                    if ((mag_work >= NEXT_EXP_MAG) && (exp_work < EXP_INF)) begin
                        sticky = sticky | mag_work[0];
                        mag_work = mag_work >> 1;
                        exp_work = exp_work + 4'd1;
                    end
                end

                if (exp_work >= EXP_INF) begin
                    result = {sign_res, EXP_INF, 3'd0};
                    flags[FLAG_OVERFLOW] = 1'b1;
                    flags[FLAG_INEXACT] = sticky;
                end else begin
                    for (norm_i = 0; norm_i < 15; norm_i = norm_i + 1) begin
                        if ((mag_work < MIN_NORMAL_MAG) && (exp_work > 4'd0)) begin
                            mag_work = mag_work << 1;
                            exp_work = exp_work - 4'd1;
                        end
                    end

                    if ((exp_work == 4'd0) || (mag_work < MIN_NORMAL_MAG)) begin
                        result = 8'd0;
                        flags[FLAG_UNDERFLOW] = 1'b1;
                        flags[FLAG_INEXACT] = sticky | (mag_work != 20'd0);
                    end else begin
                        result = {sign_res, exp_work, mag_work[10:8]};
                        flags[FLAG_INEXACT] = sticky | (mag_work[7:0] != 8'd0);
                    end
                end
            end
        end

        flags[FLAG_DIV_ZERO] = 1'b0;
        flags[FLAG_SATURATION] = 1'b0;
        flags[FLAG_UNSUPPORTED] = 1'b0;
    end

endmodule

`default_nettype wire

dr3/tp3/sim/tb_minifloat_e4m3_addsub.v
`timescale 1ns / 1ps

module tb_minifloat_e4m3_addsub;

    reg op_sub;
    reg [7:0] a;
    reg [7:0] b;
    wire [7:0] result;
    wire [5:0] flags;
    integer errors;

    minifloat_e4m3_addsub dut (
        .op_sub(op_sub),
        .a(a),
        .b(b),
        .result(result),
        .flags(flags)
    );

    initial begin
        $dumpfile("sim/build/tb_minifloat_e4m3_addsub.vcd");
        $dumpvars(0, tb_minifloat_e4m3_addsub);

        errors = 0;
        check_case(1'b0, 8'h38, 8'h30, 8'h3c, 6'b000000, "float add 1.0 + 0.5");
        check_case(1'b0, 8'h77, 8'h77, 8'h78, 6'b000001, "float add overflow to infinity");
        check_case(1'b0, 8'h38, 8'hb8, 8'h00, 6'b000000, "float add cancellation to zero");
        check_case(1'b0, 8'h08, 8'h89, 8'h00, 6'b100010, "float add underflow to zero");
        check_case(1'b1, 8'h38, 8'h30, 8'h30, 6'b000000, "float sub 1.0 - 0.5");
        check_case(1'b1, 8'h30, 8'h38, 8'hb0, 6'b000000, "float sub negative result");
        check_case(1'b1, 8'h77, 8'hf7, 8'h78, 6'b000001, "float sub overflow to infinity");
        check_case(1'b1, 8'h08, 8'h09, 8'h00, 6'b100010, "float sub underflow to zero");

        finish_test;
    end

    task check_case;
        input t_op_sub;
        input [7:0] t_a;
        input [7:0] t_b;
        input [7:0] exp_result;
        input [5:0] exp_flags;
        input [1023:0] message;
        begin
            op_sub = t_op_sub;
            a = t_a;
            b = t_b;
            #1;
            if ((result !== exp_result) || (flags !== exp_flags)) begin
                $display("FAIL: %0s result=%02h expected=%02h flags=%02h expected_flags=%02h",
                    message, result, exp_result, flags, exp_flags);
                errors = errors + 1;
            end else begin
                $display("PASS: %0s", message);
            end
        end
    endtask

    task finish_test;
        begin
            if (errors == 0) begin
                $display("ALL TESTS PASSED");
                $finish;
            end else begin
                $display("TESTS FAILED: %0d error(s)", errors);
                $fatal;
            end
        end
    endtask

endmodule

dr3/tp3/evidencias/simulacao/tb_minifloat_e4m3_addsub.vcd
$date
	Mon May 18 08:55:04 2026
$end
$version
	Icarus Verilog
$end
$timescale
	1ps
$end
$scope module tb_minifloat_e4m3_addsub $end
$var wire 8 ! result [7:0] $end
$var wire 6 " flags [5:0] $end
$var reg 8 # a [7:0] $end
$var reg 8 $ b [7:0] $end
$var reg 1 % op_sub $end
$var integer 32 & errors [31:0] $end
$scope module dut $end
$var wire 8 ' a [7:0] $end
$var wire 8 ( b [7:0] $end
$var wire 1 % op_sub $end
$var reg 22 ) abs_sum [21:0] $end
$var reg 20 * aligned_a [19:0] $end
$var reg 20 + aligned_b [19:0] $end
$var reg 4 , exp_a [3:0] $end
$var reg 4 - exp_b [3:0] $end
$var reg 5 . exp_diff [4:0] $end
$var reg 4 / exp_work [3:0] $end
$var reg 6 0 flags [5:0] $end
$var reg 4 1 frac_a [3:0] $end
$var reg 4 2 frac_b [3:0] $end
$var reg 20 3 mag_a [19:0] $end
$var reg 20 4 mag_b [19:0] $end
$var reg 20 5 mag_work [19:0] $end
$var reg 8 6 result [7:0] $end
$var reg 21 7 shifted_pack [20:0] $end
$var reg 1 8 sign_a $end
$var reg 1 9 sign_b $end
$var reg 1 : sign_b_eff $end
$var reg 1 ; sign_res $end
$var reg 22 < signed_a [21:0] $end
$var reg 22 = signed_b [21:0] $end
$var reg 1 > sticky $end
$var reg 22 ? sum_signed [21:0] $end
$var integer 32 @ norm_i [31:0] $end
$scope function shift_right_sticky $end
$var reg 5 A amount [4:0] $end
$var reg 20 B mask [19:0] $end
$var reg 20 C value [19:0] $end
$upscope $end
$upscope $end
$scope task check_case $end
$var reg 6 D exp_flags [5:0] $end
$var reg 8 E exp_result [7:0] $end
$var reg 1024 F message [1023:0] $end
$var reg 8 G t_a [7:0] $end
$var reg 8 H t_b [7:0] $end
$var reg 1 I t_op_sub $end
$upscope $end
$scope task finish_test $end
$upscope $end
$upscope $end
$enddefinitions $end
#0
$dumpvars
0I
b110000 H
b111000 G
b1100110011011000110111101100001011101000010000001100001011001000110010000100000001100010010111000110000001000000010101100100000001100000010111000110101 F
b111100 E
b0 D
b100000000000 C
b1 B
b1 A
b1111 @
b110000000000 ?
0>
b10000000000 =
b100000000000 <
0;
0:
09
08
b10000000000 7
b111100 6
b110000000000 5
b100000000000 4
b100000000000 3
b1000 2
b1000 1
b0 0
b111 /
b1 .
b110 -
b111 ,
b10000000000 +
b100000000000 *
b110000000000 )
b110000 (
b111000 '
b0 &
0%
b110000 $
b111000 #
b0 "
b111100 !
$end
#1000
b1 "
b1 0
b111100000000 C
b0 A
b101 @
b111100000000 5
b1111000000000 )
b1111000000000 ?
b111100000000 =
b111100000000 <
b111100000000 7
b111100000000 +
b111100000000 *
b111100000000 4
b111100000000 3
b0 .
b1111 2
b1111 1
b1111 /
b1110 -
b1110 ,
b1111000 !
b1111000 6
b1110111 $
b1110111 (
b1110111 #
b1110111 '
b11001100110110001101111011000010111010000100000011000010110010001100100001000000110111101110110011001010111001001100110011011000110111101110111001000000111010001101111001000000110100101101110011001100110100101101110011010010111010001111001 F
b1 D
b1111000 E
b1110111 H
b1110111 G
#2000
b100000000000 C
b0 @
b0 5
b0 )
b0 ?
b1111111111100000000000 =
b100000000000 <
b100000000000 7
b100000000000 +
b100000000000 *
b100000000000 4
b100000000000 3
b1000 2
b1000 1
b111 /
b111 -
b111 ,
1:
19
b0 "
b0 0
b0 !
b0 6
b10111000 $
b10111000 (
b111000 #
b111000 '
b11001100110110001101111011000010111010000100000011000010110010001100100001000000110001101100001011011100110001101100101011011000110110001100001011101000110100101101111011011100010000001110100011011110010000001111010011001010111001001101111 F
b0 D
b0 E
b10111000 H
b111000 G
#3000
b100010 "
b100010 0
b1111 @
b1000000000 5
b100000000 )
1;
b1111111111111100000000 ?
b100100000000 C
b1111111111011100000000 =
b100000000000 <
b100100000000 7
b100100000000 +
b100000000000 *
b100100000000 4
b100000000000 3
b1001 2
b0 /
b1 -
b1 ,
b10001001 $
b10001001 (
b1000 #
b1000 '
b11001100110110001101111011000010111010000100000011000010110010001100100001000000111010101101110011001000110010101110010011001100110110001101111011101110010000001110100011011110010000001111010011001010111001001101111 F
b100010 D
b10001001 H
b1000 G
#4000
b110000 !
b110000 6
b100000000000 C
b1 A
b1 .
b110 /
b1111 @
b100000000000 5
b10000000000 )
b10000000000 ?
b1111111111110000000000 =
b100000000000 <
b10000000000 7
b10000000000 +
b100000000000 *
b100000000000 4
b100000000000 3
b1000 2
b110 -
b111 ,
0;
09
b0 "
b0 0
b110000 $
b110000 (
b111000 #
b111000 '
1%
b1100110011011000110111101100001011101000010000001110011011101010110001000100000001100010010111000110000001000000010110100100000001100000010111000110101 F
b0 D
b110000 E
b110000 H
b111000 G
1I
#5000
1;
b1111 @
b100000000000 5
b10000000000 )
b1111111111110000000000 ?
b1111111111100000000000 =
b10000000000 <
b10000000000 7
b100000000000 +
b10000000000 *
b100000000000 4
b100000000000 3
b1 .
b110 /
b111 -
b110 ,
b10110000 !
b10110000 6
b111000 $
b111000 (
b110000 #
b110000 '
b1100110011011000110111101100001011101000010000001110011011101010110001000100000011011100110010101100111011000010111010001101001011101100110010100100000011100100110010101110011011101010110110001110100 F
b10110000 E
b111000 H
b110000 G
#6000
b1 "
b1 0
b111100000000 C
b0 A
b101 @
b111100000000 5
b1111000000000 )
b1111000000000 ?
b111100000000 =
b111100000000 <
b111100000000 7
b111100000000 +
b111100000000 *
b111100000000 4
b111100000000 3
b0 .
b1111 2
b1111 1
b1111 /
b1110 -
b1110 ,
0;
0:
19
b1111000 !
b1111000 6
b11110111 $
b11110111 (
b1110111 #
b1110111 '
b11001100110110001101111011000010111010000100000011100110111010101100010001000000110111101110110011001010111001001100110011011000110111101110111001000000111010001101111001000000110100101101110011001100110100101101110011010010111010001111001 F
b1 D
b1111000 E
b11110111 H
b1110111 G
#7000
1;
b100100000000 C
b1111 @
b1000000000 5
b100000000 )
b1111111111111100000000 ?
b1111111111011100000000 =
b100000000000 <
b100100000000 7
b100100000000 +
b100000000000 *
b100100000000 4
b100000000000 3
b1001 2
b1000 1
b0 /
b1 -
b1 ,
1:
09
b100010 "
b100010 0
b0 !
b0 6
b1001 $
b1001 (
b1000 #
b1000 '
b11001100110110001101111011000010111010000100000011100110111010101100010001000000111010101101110011001000110010101110010011001100110110001101111011101110010000001110100011011110010000001111010011001010111001001101111 F
b100010 D
b0 E
b1001 H
b1000 G
