dr1/at/rtl/code_validator.v
`timescale 1ns / 1ps

module code_validator (
    input  wire [3:0] code_in,
    output wire       code_valid
);
    // Codigo valido: 1011
    assign code_valid = code_in[3] & ~code_in[2] & code_in[1] & code_in[0];
endmodule

dr1/at/rtl/access_control.v
`timescale 1ns / 1ps

module access_control (
    input  wire       clk,
    input  wire [3:0] code_btn,
    input  wire       btn_confirm,
    input  wire       btn_reset,
    output reg        led_authorized,
    output reg        led_denied,
    output wire       led_attempt,
    output wire [2:0] led_count
);
    reg [3:0] code_meta;
    reg [3:0] code_sync;

    reg confirm_meta;
    reg confirm_sync;
    reg confirm_sync_d;

    reg reset_meta;
    reg reset_sync;

    reg [2:0] attempt_count;

    wire code_valid;
    wire confirm_pulse;

    code_validator validator (
        .code_in(code_sync),
        .code_valid(code_valid)
    );

    assign confirm_pulse = confirm_sync & ~confirm_sync_d;
    assign led_attempt = ~reset_sync & confirm_sync;
    assign led_count = attempt_count;

    // Sincroniza os botoes externos antes de usá-los na logica interna.
    always @(posedge clk) begin
        code_meta <= code_btn;
        code_sync <= code_meta;

        confirm_meta <= btn_confirm;
        confirm_sync <= confirm_meta;
        confirm_sync_d <= confirm_sync;

        reset_meta <= btn_reset;
        reset_sync <= reset_meta;
    end

    always @(posedge clk) begin
        if (reset_sync) begin
            attempt_count <= 3'b000;
            led_authorized <= 1'b0;
            led_denied <= 1'b0;
        end else if (confirm_pulse) begin
            attempt_count <= attempt_count + 3'b001;
            led_authorized <= code_valid;
            led_denied <= ~code_valid;
        end
    end
endmodule

dr1/at/tb/access_control_tb.v
`timescale 1ns / 1ps

module tb_access_control;
    reg clk;
    reg [3:0] code_btn;
    reg btn_confirm;
    reg btn_reset;

    wire led_authorized;
    wire led_denied;
    wire led_attempt;
    wire [2:0] led_count;

    access_control dut (
        .clk(clk),
        .code_btn(code_btn),
        .btn_confirm(btn_confirm),
        .btn_reset(btn_reset),
        .led_authorized(led_authorized),
        .led_denied(led_denied),
        .led_attempt(led_attempt),
        .led_count(led_count)
    );

    always #5 clk = ~clk;

    task automatic expect_outputs;
        input [8*40-1:0] label;
        input [2:0] expected_count;
        input expected_authorized;
        input expected_denied;
        begin
            if (led_count !== expected_count) begin
                $fatal(1, "FALHA (%0s): contador = %b, esperado = %b, tempo = %0t",
                    label, led_count, expected_count, $time);
            end

            if (led_authorized !== expected_authorized) begin
                $fatal(1, "FALHA (%0s): LED0 = %b, esperado = %b, tempo = %0t",
                    label, led_authorized, expected_authorized, $time);
            end

            if (led_denied !== expected_denied) begin
                $fatal(1, "FALHA (%0s): LED1 = %b, esperado = %b, tempo = %0t",
                    label, led_denied, expected_denied, $time);
            end
        end
    endtask

    task automatic settle_code;
        input [3:0] value;
        begin
            code_btn = value;
            repeat (3) @(posedge clk);
            #1;
        end
    endtask

    task automatic attempt_code;
        input [8*40-1:0] label;
        input [3:0] value;
        input expected_authorized;
        input expected_denied;
        input [2:0] expected_count;
        input integer hold_cycles;
        begin
            settle_code(value);

            btn_confirm = 1'b1;
            repeat (hold_cycles) @(posedge clk);
            #1;

            if (led_attempt !== 1'b1) begin
                $fatal(1, "FALHA (%0s): LED2 deveria indicar tentativa durante BTN1 ativo, tempo = %0t",
                    label, $time);
            end

            btn_confirm = 1'b0;
            repeat (3) @(posedge clk);
            #1;

            if (led_attempt !== 1'b0) begin
                $fatal(1, "FALHA (%0s): LED2 deveria apagar apos a liberacao de BTN1, tempo = %0t",
                    label, $time);
            end

            expect_outputs(label, expected_count, expected_authorized, expected_denied);
        end
    endtask

    task automatic apply_reset;
        input [8*40-1:0] label;
        begin
            btn_reset = 1'b1;
            repeat (3) @(posedge clk);
            #1;

            if ({led_authorized, led_denied, led_attempt, led_count} !== 6'b000000) begin
                $fatal(1, "FALHA (%0s): reset nao limpou imediatamente as saidas esperadas, tempo = %0t",
                    label, $time);
            end

            btn_reset = 1'b0;
            repeat (3) @(posedge clk);
            #1;

            if (led_attempt !== 1'b0) begin
                $fatal(1, "FALHA (%0s): LED2 deveria permanecer apagado apos reset, tempo = %0t",
                    label, $time);
            end

            expect_outputs(label, 3'b000, 1'b0, 1'b0);
        end
    endtask

    initial begin
        $dumpfile("sim/vcd/access_control.vcd");
        $dumpvars(0, tb_access_control);

        clk = 1'b0;
        code_btn = 4'b0000;
        btn_confirm = 1'b0;
        btn_reset = 1'b0;

        repeat (2) @(posedge clk);

        apply_reset("reset_inicial");

        attempt_code("codigo_correto", 4'b1011, 1'b1, 1'b0, 3'b001, 4);
        attempt_code("codigo_incorreto", 4'b0101, 1'b0, 1'b1, 3'b010, 4);
        attempt_code("multiplas_1", 4'b0000, 1'b0, 1'b1, 3'b011, 6);
        attempt_code("multiplas_2", 4'b1011, 1'b1, 1'b0, 3'b100, 4);

        apply_reset("reset_final");

        $display("SIMULACAO_OK");
        $finish;
    end
endmodule

dr1/at/sim/vcd/access_control.vcd
$date
	Sun Apr  5 16:42:36 2026
$end
$version
	Icarus Verilog
$end
$timescale
	1ps
$end
$scope module tb_access_control $end
$var wire 1 ! led_denied $end
$var wire 3 " led_count [2:0] $end
$var wire 1 # led_authorized $end
$var wire 1 $ led_attempt $end
$var reg 1 % btn_confirm $end
$var reg 1 & btn_reset $end
$var reg 1 ' clk $end
$var reg 4 ( code_btn [3:0] $end
$scope module dut $end
$var wire 1 % btn_confirm $end
$var wire 1 & btn_reset $end
$var wire 1 ' clk $end
$var wire 4 ) code_btn [3:0] $end
$var wire 1 * confirm_pulse $end
$var wire 1 $ led_attempt $end
$var wire 3 + led_count [2:0] $end
$var wire 1 , code_valid $end
$var reg 3 - attempt_count [2:0] $end
$var reg 4 . code_meta [3:0] $end
$var reg 4 / code_sync [3:0] $end
$var reg 1 0 confirm_meta $end
$var reg 1 1 confirm_sync $end
$var reg 1 2 confirm_sync_d $end
$var reg 1 # led_authorized $end
$var reg 1 ! led_denied $end
$var reg 1 3 reset_meta $end
$var reg 1 4 reset_sync $end
$scope module validator $end
$var wire 4 5 code_in [3:0] $end
$var wire 1 , code_valid $end
$upscope $end
$upscope $end
$scope task apply_reset $end
$upscope $end
$scope task attempt_code $end
$upscope $end
$scope task expect_outputs $end
$upscope $end
$scope task settle_code $end
$upscope $end
$upscope $end
$enddefinitions $end
#0
$dumpvars
bx 5
x4
x3
x2
x1
x0
bx /
bx .
bx -
x,
bx +
x*
b0 )
b0 (
0'
0&
0%
x$
x#
bx "
x!
$end
#5000
03
00
b0 .
1'
#10000
0'
#15000
0,
0$
0*
04
01
b0 /
b0 5
1&
1'
#20000
0'
#25000
13
02
1'
#30000
0'
#35000
14
1'
#40000
0'
#45000
0!
0#
b0 "
b0 +
b0 -
1'
#46000
0&
#50000
0'
#55000
03
1'
#60000
0'
#65000
04
1'
#70000
0'
#75000
1'
#76000
b1011 (
b1011 )
#80000
0'
#85000
b1011 .
1'
#90000
0'
#95000
1,
b1011 /
b1011 5
1'
#100000
0'
#105000
1'
#106000
1%
#110000
0'
#115000
10
1'
#120000
0'
#125000
1$
1*
11
1'
#130000
0'
#135000
0*
1#
b1 "
b1 +
b1 -
12
1'
#140000
0'
#145000
1'
#146000
0%
#150000
0'
#155000
00
1'
#160000
0'
#165000
0$
01
1'
#170000
0'
#175000
02
1'
#176000
b101 (
b101 )
#180000
0'
#185000
b101 .
1'
#190000
0'
#195000
0,
b101 /
b101 5
1'
#200000
0'
#205000
1'
#206000
1%
#210000
0'
#215000
10
1'
#220000
0'
#225000
1$
1*
11
1'
#230000
0'
#235000
0*
1!
0#
b10 "
b10 +
b10 -
12
1'
#240000
0'
#245000
1'
#246000
0%
#250000
0'
#255000
00
1'
#260000
0'
#265000
0$
01
1'
#270000
0'
#275000
02
1'
#276000
b0 (
b0 )
#280000
0'
#285000
b0 .
1'
#290000
0'
#295000
b0 /
b0 5
1'
#300000
0'
#305000
1'
#306000
1%
#310000
0'
#315000
10
1'
#320000
0'
#325000
1$
1*
11
1'
#330000
0'
#335000
0*
b11 "
b11 +
b11 -
12
1'
#340000
0'
#345000
1'
#350000
0'
#355000
1'
#360000
0'
#365000
1'
#366000
0%
#370000
0'
#375000
00
1'
#380000
0'
#385000
0$
01
1'
#390000
0'
#395000
02
1'
#396000
b1011 (
b1011 )
#400000
0'
#405000
b1011 .
1'
#410000
0'
#415000
1,
b1011 /
b1011 5
1'
#420000
0'
#425000
1'
#426000
1%
#430000
0'
#435000
10
1'
#440000
0'
#445000
1$
1*
11
1'
#450000
0'
#455000
0*
0!
1#
b100 "
b100 +
b100 -
12
1'
#460000
0'
#465000
1'
#466000
0%
#470000
0'
#475000
00
1'
#480000
0'
#485000
0$
01
1'
#490000
0'
#495000
02
1'
#496000
1&
#500000
0'
#505000
13
1'
#510000
0'
#515000
14
1'
#520000
0'
#525000
0#
b0 "
b0 +
b0 -
1'
#526000
0&
#530000
0'
#535000
03
1'
#540000
0'
#545000
04
1'
